Workbook

Sheet Reporting Hebdo
D1: Reporting Cash Hebdomadaire – Centralisation Côte d'Ivoire
C2: Soldes bancaires au | E2: 46295 | M2: Semaine | N2: S1 | P2: S2 | R2: S3 | T2: S4 | V2: S5
C3: Taux FCFA / € | E3: 655.957 | M3: Du | N3: 46300 | P3: =N3+7 | R3: =P3+7 | T3: =R3+7 | V3: =T3+7
C4: Édité le | E4: 46302 | M4: Au | N4: =N3+6 | P4: =P3+6 | R4: =R3+6 | T4: =T3+6 | V4: =V3+6
C6: Soldes Bancaires (Réel) – Comptes de sociétés
F8: En euros | G8: S1 | H8: S2 | I8: S3 | J8: S4 | K8: S5 | M8: En FCFA | N8: S1 | P8: S2 | R8: S3 | T8: S4 | V8: S5
F9: =$E$2 | G9: =N4 | H9: =P4 | I9: =R4 | J9: =T4 | K9: =V4 | M9: =$E$2 | N9: =N3 | O9: =N4 | P9: =P3 | Q9: =P4 | R9: =R3 | S9: =R4 | T9: =T3 | U9: =T4 | V9: =V3 | W9: =V4 | Y9: COMMENTAIRES
C10: BANQUE | D10: Destination (position CI) | F10: Solde réel | G10: Solde théorique | H10: Solde théorique | I10: Solde théorique | J10: Solde théorique | K10: Solde théorique | M10: Solde réel | N10: Prévisions (flux) | O10: Solde théorique | P10: Prévisions (flux) | Q10: Solde théorique | R10: Prévisions (flux) | S10: Solde théorique | T10: Prévisions (flux) | U10: Solde théorique | V10: Prévisions (flux) | W10: Solde théorique
A11: PICI | C11: PROMOTION (PICI) | F11: =M11/$E$3 | G11: =O11/$E$3 | H11: =Q11/$E$3 | I11: =S11/$E$3 | J11: =U11/$E$3 | K11: =W11/$E$3 | M11: =SUM(M12:M14) | N11: =SUMIFS('Détail fonctionnement'!$J$5:$J$505,'Détail fonctionnement'!$A$5:$A$505,N$2,'Détail fonctionnement'!$G$5:$G$505,"O",'Détail fonctionnement'!$B$5:$B$505,$A11) | O11: =M11+N11 | P11: =SUMIFS('Détail fonctionnement'!$J$5:$J$505,'Détail fonctionnement'!$A$5:$A$505,P$2,'Détail fonctionnement'!$G$5:$G$505,"O",'Détail fonctionnement'!$B$5:$B$505,$A11) | Q11: =O11+P11 | R11: =SUMIFS('Détail fonctionnement'!$J$5:$J$505,'Détail fonctionnement'!$A$5:$A$505,R$2,'Détail fonctionnement'!$G$5:$G$505,"O",'Détail fonctionnement'!$B$5:$B$505,$A11) | S11: =Q11+R11 | T11: =SUMIFS('Détail fonctionnement'!$J$5:$J$505,'Détail fonctionnement'!$A$5:$A$505,T$2,'Détail fonctionnement'!$G$5:$G$505,"O",'Détail fonctionnement'!$B$5:$B$505,$A11) | U11: =S11+T11 | V11: =SUMIFS('Détail fonctionnement'!$J$5:$J$505,'Détail fonctionnement'!$A$5:$A$505,V$2,'Détail fonctionnement'!$G$5:$G$505,"O",'Détail fonctionnement'!$B$5:$B$505,$A11) | W11: =U11+V11
C12: SOCIETE GENERALE-PICI | D12: Dédié besoin de fonctionnement et "Netting" autres compagnies CIV | F12: =M12/$E$3 | M12: ='Position CI 30-09'!F5
C13: STANBIC-PICI | D13: Dédié besoin de fonctionnement | F13: =M13/$E$3 | M13: ='Position CI 30-09'!F6
C14: ECOBANK-PICI | D14: Dédié besoin de fonctionnement | F14: =M14/$E$3 | M14: ='Position CI 30-09'!F7
A15: FIRST | C15: PROPERTY (SCI FIRST) | F15: =M15/$E$3 | G15: =O15/$E$3 | H15: =Q15/$E$3 | I15: =S15/$E$3 | J15: =U15/$E$3 | K15: =W15/$E$3 | M15: =SUM(M16:M17) | N15: =SUMIFS('Détail fonctionnement'!$J$5:$J$505,'Détail fonctionnement'!$A$5:$A$505,N$2,'Détail fonctionnement'!$G$5:$G$505,"O",'Détail fonctionnement'!$B$5:$B$505,$A15) | O15: =M15+N15 | P15: =SUMIFS('Détail fonctionnement'!$J$5:$J$505,'Détail fonctionnement'!$A$5:$A$505,P$2,'Détail fonctionnement'!$G$5:$G$505,"O",'Détail fonctionnement'!$B$5:$B$505,$A15) | Q15: =O15+P15 | R15: =SUMIFS('Détail fonctionnement'!$J$5:$J$505,'Détail fonctionnement'!$A$5:$A$505,R$2,'Détail fonctionnement'!$G$5:$G$505,"O",'Détail fonctionnement'!$B$5:$B$505,$A15) | S15: =Q15+R15 | T15: =SUMIFS('Détail fonctionnement'!$J$5:$J$505,'Détail fonctionnement'!$A$5:$A$505,T$2,'Détail fonctionnement'!$G$5:$G$505,"O",'Détail fonctionnement'!$B$5:$B$505,$A15) | U15: =S15+T15 | V15: =SUMIFS('Détail fonctionnement'!$J$5:$J$505,'Détail fonctionnement'!$A$5:$A$505,V$2,'Détail fonctionnement'!$G$5:$G$505,"O",'Détail fonctionnement'!$B$5:$B$505,$A15) | W15: =U15+V15
C16: SOCIETE GENERALE-FIRST | D16: Dédié besoin de fonctionnement | F16: =M16/$E$3 | M16: ='Position CI 30-09'!F8
C17: STANBIC-FIRST | D17: Dédié besoin de fonctionnement | F17: =M17/$E$3 | M17: ='Position CI 30-09'!F9
A18: TERASSON | C18: TERASSON | F18: =M18/$E$3 | G18: =O18/$E$3 | H18: =Q18/$E$3 | I18: =S18/$E$3 | J18: =U18/$E$3 | K18: =W18/$E$3 | M18: =SUM(M19:M20) | N18: =SUMIFS('Détail fonctionnement'!$J$5:$J$505,'Détail fonctionnement'!$A$5:$A$505,N$2,'Détail fonctionnement'!$G$5:$G$505,"O",'Détail fonctionnement'!$B$5:$B$505,$A18) | O18: =M18+N18 | P18: =SUMIFS('Détail fonctionnement'!$J$5:$J$505,'Détail fonctionnement'!$A$5:$A$505,P$2,'Détail fonctionnement'!$G$5:$G$505,"O",'Détail fonctionnement'!$B$5:$B$505,$A18) | Q18: =O18+P18 | R18: =SUMIFS('Détail fonctionnement'!$J$5:$J$505,'Détail fonctionnement'!$A$5:$A$505,R$2,'Détail fonctionnement'!$G$5:$G$505,"O",'Détail fonctionnement'!$B$5:$B$505,$A18) | S18: =Q18+R18 | T18: =SUMIFS('Détail fonctionnement'!$J$5:$J$505,'Détail fonctionnement'!$A$5:$A$505,T$2,'Détail fonctionnement'!$G$5:$G$505,"O",'Détail fonctionnement'!$B$5:$B$505,$A18) | U18: =S18+T18 | V18: =SUMIFS('Détail fonctionnement'!$J$5:$J$505,'Détail fonctionnement'!$A$5:$A$505,V$2,'Détail fonctionnement'!$G$5:$G$505,"O",'Détail fonctionnement'!$B$5:$B$505,$A18) | W18: =U18+V18
C19: SOCIETE GENERALE-TERASSON | D19: Dédié besoin de fonctionnement | F19: =M19/$E$3 | M19: ='Position CI 30-09'!F10
C20: ECOBANK -TERASSON | D20: Dédié besoin de fonctionnement | F20: =M20/$E$3 | M20: ='Position CI 30-09'!F11
A21: RIVIERA | C21: RIVIERA PARK | F21: =M21/$E$3 | G21: =O21/$E$3 | H21: =Q21/$E$3 | I21: =S21/$E$3 | J21: =U21/$E$3 | K21: =W21/$E$3 | M21: =SUM(M22:M22) | N21: =SUMIFS('Détail fonctionnement'!$J$5:$J$505,'Détail fonctionnement'!$A$5:$A$505,N$2,'Détail fonctionnement'!$G$5:$G$505,"O",'Détail fonctionnement'!$B$5:$B$505,$A21) | O21: =M21+N21 | P21: =SUMIFS('Détail fonctionnement'!$J$5:$J$505,'Détail fonctionnement'!$A$5:$A$505,P$2,'Détail fonctionnement'!$G$5:$G$505,"O",'Détail fonctionnement'!$B$5:$B$505,$A21) | Q21: =O21+P21 | R21: =SUMIFS('Détail fonctionnement'!$J$5:$J$505,'Détail fonctionnement'!$A$5:$A$505,R$2,'Détail fonctionnement'!$G$5:$G$505,"O",'Détail fonctionnement'!$B$5:$B$505,$A21) | S21: =Q21+R21 | T21: =SUMIFS('Détail fonctionnement'!$J$5:$J$505,'Détail fonctionnement'!$A$5:$A$505,T$2,'Détail fonctionnement'!$G$5:$G$505,"O",'Détail fonctionnement'!$B$5:$B$505,$A21) | U21: =S21+T21 | V21: =SUMIFS('Détail fonctionnement'!$J$5:$J$505,'Détail fonctionnement'!$A$5:$A$505,V$2,'Détail fonctionnement'!$G$5:$G$505,"O",'Détail fonctionnement'!$B$5:$B$505,$A21) | W21: =U21+V21
C22: SOCIETE GENERALE-RIVIERA | D22: Dédié besoin de fonctionnement | F22: =M22/$E$3 | M22: ='Position CI 30-09'!F12
A23: SCO AO | C23: SCO AO | F23: =M23/$E$3 | G23: =O23/$E$3 | H23: =Q23/$E$3 | I23: =S23/$E$3 | J23: =U23/$E$3 | K23: =W23/$E$3 | M23: =SUM(M24:M28) | N23: =SUMIFS('Détail fonctionnement'!$J$5:$J$505,'Détail fonctionnement'!$A$5:$A$505,N$2,'Détail fonctionnement'!$G$5:$G$505,"O",'Détail fonctionnement'!$B$5:$B$505,$A23) | O23: =M23+N23 | P23: =SUMIFS('Détail fonctionnement'!$J$5:$J$505,'Détail fonctionnement'!$A$5:$A$505,P$2,'Détail fonctionnement'!$G$5:$G$505,"O",'Détail fonctionnement'!$B$5:$B$505,$A23) | Q23: =O23+P23 | R23: =SUMIFS('Détail fonctionnement'!$J$5:$J$505,'Détail fonctionnement'!$A$5:$A$505,R$2,'Détail fonctionnement'!$G$5:$G$505,"O",'Détail fonctionnement'!$B$5:$B$505,$A23) | S23: =Q23+R23 | T23: =SUMIFS('Détail fonctionnement'!$J$5:$J$505,'Détail fonctionnement'!$A$5:$A$505,T$2,'Détail fonctionnement'!$G$5:$G$505,"O",'Détail fonctionnement'!$B$5:$B$505,$A23) | U23: =S23+T23 | V23: =SUMIFS('Détail fonctionnement'!$J$5:$J$505,'Détail fonctionnement'!$A$5:$A$505,V$2,'Détail fonctionnement'!$G$5:$G$505,"O",'Détail fonctionnement'!$B$5:$B$505,$A23) | W23: =U23+V23
C24: BANK OF AFRICA-SCO AO | D24: Dédié besoin de fonctionnement | F24: =M24/$E$3 | M24: ='Position CI 30-09'!F14
C25: BACI-CompteCourant | D25: Dédié besoin de fonctionnement | F25: =M25/$E$3 | M25: ='Position CI 30-09'!F15
C26: BACI-Projet | D26: Dédié paiement Projet SCO | F26: =M26/$E$3 | M26: ='Position CI 30-09'!F16
C27: BACI-AGORA | D27: Dédié paiement Projet SCO | F27: =M27/$E$3 | M27: ='Position CI 30-09'!F17
C28: ECOBANK - SCO AO | D28: Dédié besoin de fonctionnement | F28: =M28/$E$3 | M28: ='Position CI 30-09'!F18
A29: FINAFRICA | C29: FINAFRICA CI | F29: =M29/$E$3 | G29: =O29/$E$3 | H29: =Q29/$E$3 | I29: =S29/$E$3 | J29: =U29/$E$3 | K29: =W29/$E$3 | M29: =SUM(M30:M31) | N29: =SUMIFS('Détail fonctionnement'!$J$5:$J$505,'Détail fonctionnement'!$A$5:$A$505,N$2,'Détail fonctionnement'!$G$5:$G$505,"O",'Détail fonctionnement'!$B$5:$B$505,$A29) | O29: =M29+N29 | P29: =SUMIFS('Détail fonctionnement'!$J$5:$J$505,'Détail fonctionnement'!$A$5:$A$505,P$2,'Détail fonctionnement'!$G$5:$G$505,"O",'Détail fonctionnement'!$B$5:$B$505,$A29) | Q29: =O29+P29 | R29: =SUMIFS('Détail fonctionnement'!$J$5:$J$505,'Détail fonctionnement'!$A$5:$A$505,R$2,'Détail fonctionnement'!$G$5:$G$505,"O",'Détail fonctionnement'!$B$5:$B$505,$A29) | S29: =Q29+R29 | T29: =SUMIFS('Détail fonctionnement'!$J$5:$J$505,'Détail fonctionnement'!$A$5:$A$505,T$2,'Détail fonctionnement'!$G$5:$G$505,"O",'Détail fonctionnement'!$B$5:$B$505,$A29) | U29: =S29+T29 | V29: =SUMIFS('Détail fonctionnement'!$J$5:$J$505,'Détail fonctionnement'!$A$5:$A$505,V$2,'Détail fonctionnement'!$G$5:$G$505,"O",'Détail fonctionnement'!$B$5:$B$505,$A29) | W29: =U29+V29
C30: SOCIETE GENERALE-FINAFRICA | D30: Dédié besoin de fonctionnement | F30: =M30/$E$3 | M30: ='Position CI 30-09'!F19
C31: ECOBANK-FINAFRICA | D31: Dédié besoin de fonctionnement | F31: =M31/$E$3 | M31: ='Position CI 30-09'!F20
A32: AB CENTER | C32: AB CENTER | F32: =M32/$E$3 | G32: =O32/$E$3 | H32: =Q32/$E$3 | I32: =S32/$E$3 | J32: =U32/$E$3 | K32: =W32/$E$3 | M32: =SUM(M33:M34) | N32: =SUMIFS('Détail fonctionnement'!$J$5:$J$505,'Détail fonctionnement'!$A$5:$A$505,N$2,'Détail fonctionnement'!$G$5:$G$505,"O",'Détail fonctionnement'!$B$5:$B$505,$A32) | O32: =M32+N32 | P32: =SUMIFS('Détail fonctionnement'!$J$5:$J$505,'Détail fonctionnement'!$A$5:$A$505,P$2,'Détail fonctionnement'!$G$5:$G$505,"O",'Détail fonctionnement'!$B$5:$B$505,$A32) | Q32: =O32+P32 | R32: =SUMIFS('Détail fonctionnement'!$J$5:$J$505,'Détail fonctionnement'!$A$5:$A$505,R$2,'Détail fonctionnement'!$G$5:$G$505,"O",'Détail fonctionnement'!$B$5:$B$505,$A32) | S32: =Q32+R32 | T32: =SUMIFS('Détail fonctionnement'!$J$5:$J$505,'Détail fonctionnement'!$A$5:$A$505,T$2,'Détail fonctionnement'!$G$5:$G$505,"O",'Détail fonctionnement'!$B$5:$B$505,$A32) | U32: =S32+T32 | V32: =SUMIFS('Détail fonctionnement'!$J$5:$J$505,'Détail fonctionnement'!$A$5:$A$505,V$2,'Détail fonctionnement'!$G$5:$G$505,"O",'Détail fonctionnement'!$B$5:$B$505,$A32) | W32: =U32+V32
C33: SOCIETE GENERALE-AB CENTER | D33: Dédié besoin de fonctionnement | F33: =M33/$E$3 | M33: ='Position CI 30-09'!F21
C34: ECOBANK- AB CENTER | D34: Dédié besoin de fonctionnement | F34: =M34/$E$3 | M34: ='Position CI 30-09'!F22
A35: IMMONEUF | C35: IMMONEUF | F35: =M35/$E$3 | G35: =O35/$E$3 | H35: =Q35/$E$3 | I35: =S35/$E$3 | J35: =U35/$E$3 | K35: =W35/$E$3 | M35: =SUM(M36:M38) | N35: =SUMIFS('Détail fonctionnement'!$J$5:$J$505,'Détail fonctionnement'!$A$5:$A$505,N$2,'Détail fonctionnement'!$G$5:$G$505,"O",'Détail fonctionnement'!$B$5:$B$505,$A35) | O35: =M35+N35 | P35: =SUMIFS('Détail fonctionnement'!$J$5:$J$505,'Détail fonctionnement'!$A$5:$A$505,P$2,'Détail fonctionnement'!$G$5:$G$505,"O",'Détail fonctionnement'!$B$5:$B$505,$A35) | Q35: =O35+P35 | R35: =SUMIFS('Détail fonctionnement'!$J$5:$J$505,'Détail fonctionnement'!$A$5:$A$505,R$2,'Détail fonctionnement'!$G$5:$G$505,"O",'Détail fonctionnement'!$B$5:$B$505,$A35) | S35: =Q35+R35 | T35: =SUMIFS('Détail fonctionnement'!$J$5:$J$505,'Détail fonctionnement'!$A$5:$A$505,T$2,'Détail fonctionnement'!$G$5:$G$505,"O",'Détail fonctionnement'!$B$5:$B$505,$A35) | U35: =S35+T35 | V35: =SUMIFS('Détail fonctionnement'!$J$5:$J$505,'Détail fonctionnement'!$A$5:$A$505,V$2,'Détail fonctionnement'!$G$5:$G$505,"O",'Détail fonctionnement'!$B$5:$B$505,$A35) | W35: =U35+V35
C36: SOCIETE GENERALE-IMMONEUF | D36: Dédié besoin de fonctionnement | F36: =M36/$E$3 | M36: ='Position CI 30-09'!F23
C37: ECOBANK-IMMONEUF | D37: Dédié besoin de fonctionnement | F37: =M37/$E$3 | M37: ='Position CI 30-09'!F24
C38: BACI - IMMONEUF | D38: Dédié besoin de fonctionnement | F38: =M38/$E$3 | M38: ='Position CI 30-09'!F25
A39: INFI SOFT | C39: INFI SOFT | F39: =M39/$E$3 | G39: =O39/$E$3 | H39: =Q39/$E$3 | I39: =S39/$E$3 | J39: =U39/$E$3 | K39: =W39/$E$3 | M39: =SUM(M40:M40) | N39: =SUMIFS('Détail fonctionnement'!$J$5:$J$505,'Détail fonctionnement'!$A$5:$A$505,N$2,'Détail fonctionnement'!$G$5:$G$505,"O",'Détail fonctionnement'!$B$5:$B$505,$A39) | O39: =M39+N39 | P39: =SUMIFS('Détail fonctionnement'!$J$5:$J$505,'Détail fonctionnement'!$A$5:$A$505,P$2,'Détail fonctionnement'!$G$5:$G$505,"O",'Détail fonctionnement'!$B$5:$B$505,$A39) | Q39: =O39+P39 | R39: =SUMIFS('Détail fonctionnement'!$J$5:$J$505,'Détail fonctionnement'!$A$5:$A$505,R$2,'Détail fonctionnement'!$G$5:$G$505,"O",'Détail fonctionnement'!$B$5:$B$505,$A39) | S39: =Q39+R39 | T39: =SUMIFS('Détail fonctionnement'!$J$5:$J$505,'Détail fonctionnement'!$A$5:$A$505,T$2,'Détail fonctionnement'!$G$5:$G$505,"O",'Détail fonctionnement'!$B$5:$B$505,$A39) | U39: =S39+T39 | V39: =SUMIFS('Détail fonctionnement'!$J$5:$J$505,'Détail fonctionnement'!$A$5:$A$505,V$2,'Détail fonctionnement'!$G$5:$G$505,"O",'Détail fonctionnement'!$B$5:$B$505,$A39) | W39: =U39+V39
C40: INFI SOFT - SIB | D40: Dédié besoin de fonctionnement | F40: =M40/$E$3 | M40: ='Position CI 30-09'!F26
A41: ODALYS CI | C41: ODALYS CI | F41: =M41/$E$3 | G41: =O41/$E$3 | H41: =Q41/$E$3 | I41: =S41/$E$3 | J41: =U41/$E$3 | K41: =W41/$E$3 | M41: =SUM(M42:M42) | N41: =SUMIFS('Détail fonctionnement'!$J$5:$J$505,'Détail fonctionnement'!$A$5:$A$505,N$2,'Détail fonctionnement'!$G$5:$G$505,"O",'Détail fonctionnement'!$B$5:$B$505,$A41) | O41: =M41+N41 | P41: =SUMIFS('Détail fonctionnement'!$J$5:$J$505,'Détail fonctionnement'!$A$5:$A$505,P$2,'Détail fonctionnement'!$G$5:$G$505,"O",'Détail fonctionnement'!$B$5:$B$505,$A41) | Q41: =O41+P41 | R41: =SUMIFS('Détail fonctionnement'!$J$5:$J$505,'Détail fonctionnement'!$A$5:$A$505,R$2,'Détail fonctionnement'!$G$5:$G$505,"O",'Détail fonctionnement'!$B$5:$B$505,$A41) | S41: =Q41+R41 | T41: =SUMIFS('Détail fonctionnement'!$J$5:$J$505,'Détail fonctionnement'!$A$5:$A$505,T$2,'Détail fonctionnement'!$G$5:$G$505,"O",'Détail fonctionnement'!$B$5:$B$505,$A41) | U41: =S41+T41 | V41: =SUMIFS('Détail fonctionnement'!$J$5:$J$505,'Détail fonctionnement'!$A$5:$A$505,V$2,'Détail fonctionnement'!$G$5:$G$505,"O",'Détail fonctionnement'!$B$5:$B$505,$A41) | W41: =U41+V41
C42: SOCIETE GENERALE-ODALYS | D42: Dédié besoin de fonctionnement | F42: =M42/$E$3 | M42: ='Position CI 30-09'!F27
A43: RHD CI | C43: RHD CI | F43: =M43/$E$3 | G43: =O43/$E$3 | H43: =Q43/$E$3 | I43: =S43/$E$3 | J43: =U43/$E$3 | K43: =W43/$E$3 | M43: 0 | N43: =SUMIFS('Détail fonctionnement'!$J$5:$J$505,'Détail fonctionnement'!$A$5:$A$505,N$2,'Détail fonctionnement'!$G$5:$G$505,"O",'Détail fonctionnement'!$B$5:$B$505,$A43) | O43: =M43+N43 | P43: =SUMIFS('Détail fonctionnement'!$J$5:$J$505,'Détail fonctionnement'!$A$5:$A$505,P$2,'Détail fonctionnement'!$G$5:$G$505,"O",'Détail fonctionnement'!$B$5:$B$505,$A43) | Q43: =O43+P43 | R43: =SUMIFS('Détail fonctionnement'!$J$5:$J$505,'Détail fonctionnement'!$A$5:$A$505,R$2,'Détail fonctionnement'!$G$5:$G$505,"O",'Détail fonctionnement'!$B$5:$B$505,$A43) | S43: =Q43+R43 | T43: =SUMIFS('Détail fonctionnement'!$J$5:$J$505,'Détail fonctionnement'!$A$5:$A$505,T$2,'Détail fonctionnement'!$G$5:$G$505,"O",'Détail fonctionnement'!$B$5:$B$505,$A43) | U43: =S43+T43 | V43: =SUMIFS('Détail fonctionnement'!$J$5:$J$505,'Détail fonctionnement'!$A$5:$A$505,V$2,'Détail fonctionnement'!$G$5:$G$505,"O",'Détail fonctionnement'!$B$5:$B$505,$A43) | W43: =U43+V43
C44: TOTAL COMPTES DE SOCIÉTÉS | F44: =F11+F15+F18+F21+F23+F29+F32+F35+F39+F41+F43 | G44: =G11+G15+G18+G21+G23+G29+G32+G35+G39+G41+G43 | H44: =H11+H15+H18+H21+H23+H29+H32+H35+H39+H41+H43 | I44: =I11+I15+I18+I21+I23+I29+I32+I35+I39+I41+I43 | J44: =J11+J15+J18+J21+J23+J29+J32+J35+J39+J41+J43 | K44: =K11+K15+K18+K21+K23+K29+K32+K35+K39+K41+K43 | M44: =M11+M15+M18+M21+M23+M29+M32+M35+M39+M41+M43 | N44: =N11+N15+N18+N21+N23+N29+N32+N35+N39+N41+N43 | O44: =O11+O15+O18+O21+O23+O29+O32+O35+O39+O41+O43 | P44: =P11+P15+P18+P21+P23+P29+P32+P35+P39+P41+P43 | Q44: =Q11+Q15+Q18+Q21+Q23+Q29+Q32+Q35+Q39+Q41+Q43 | R44: =R11+R15+R18+R21+R23+R29+R32+R35+R39+R41+R43 | S44: =S11+S15+S18+S21+S23+S29+S32+S35+S39+S41+S43 | T44: =T11+T15+T18+T21+T23+T29+T32+T35+T39+T41+T43 | ... W44: =W11+W15+W18+W21+W23+W29+W32+W35+W39+W41+W43
C46: Soldes Bancaires (Réel) – Comptes dédiés (projets et remboursement de dettes)
A47: RIVIERA-ARBITRER | C47: BNI-RIVIERA(Courant) | D47: À arbitrer (« Affection placement? Ou besoin de fonctionnement ») | F47: =M47/$E$3 | G47: =O47/$E$3 | H47: =Q47/$E$3 | I47: =S47/$E$3 | J47: =U47/$E$3 | K47: =W47/$E$3 | M47: ='Position CI 30-09'!F13 | N47: =SUMIFS('Détail projets & dettes'!$M$5:$M$500,'Détail projets & dettes'!$A$5:$A$500,N$2,'Détail projets & dettes'!$J$5:$J$500,"O",'Détail projets & dettes'!$B$5:$B$500,$A47) | O47: =M47+N47 | P47: =SUMIFS('Détail projets & dettes'!$M$5:$M$500,'Détail projets & dettes'!$A$5:$A$500,P$2,'Détail projets & dettes'!$J$5:$J$500,"O",'Détail projets & dettes'!$B$5:$B$500,$A47) | Q47: =O47+P47 | R47: =SUMIFS('Détail projets & dettes'!$M$5:$M$500,'Détail projets & dettes'!$A$5:$A$500,R$2,'Détail projets & dettes'!$J$5:$J$500,"O",'Détail projets & dettes'!$B$5:$B$500,$A47) | S47: =Q47+R47 | T47: =SUMIFS('Détail projets & dettes'!$M$5:$M$500,'Détail projets & dettes'!$A$5:$A$500,T$2,'Détail projets & dettes'!$J$5:$J$500,"O",'Détail projets & dettes'!$B$5:$B$500,$A47) | U47: =S47+T47 | V47: =SUMIFS('Détail projets & dettes'!$M$5:$M$500,'Détail projets & dettes'!$A$5:$A$500,V$2,'Détail projets & dettes'!$J$5:$J$500,"O",'Détail projets & dettes'!$B$5:$B$500,$A47) | W47: =U47+V47
A48: RIVIERA-PROJET | C48: BNI-PICI / Fonds projet RP | D48: Fonds projet (paiement CPI) | F48: =M48/$E$3 | G48: =O48/$E$3 | H48: =Q48/$E$3 | I48: =S48/$E$3 | J48: =U48/$E$3 | K48: =W48/$E$3 | M48: ='Position CI 30-09'!F28 | N48: =SUMIFS('Détail projets & dettes'!$M$5:$M$500,'Détail projets & dettes'!$A$5:$A$500,N$2,'Détail projets & dettes'!$J$5:$J$500,"O",'Détail projets & dettes'!$B$5:$B$500,$A48) | O48: =M48+N48 | P48: =SUMIFS('Détail projets & dettes'!$M$5:$M$500,'Détail projets & dettes'!$A$5:$A$500,P$2,'Détail projets & dettes'!$J$5:$J$500,"O",'Détail projets & dettes'!$B$5:$B$500,$A48) | Q48: =O48+P48 | R48: =SUMIFS('Détail projets & dettes'!$M$5:$M$500,'Détail projets & dettes'!$A$5:$A$500,R$2,'Détail projets & dettes'!$J$5:$J$500,"O",'Détail projets & dettes'!$B$5:$B$500,$A48) | S48: =Q48+R48 | T48: =SUMIFS('Détail projets & dettes'!$M$5:$M$500,'Détail projets & dettes'!$A$5:$A$500,T$2,'Détail projets & dettes'!$J$5:$J$500,"O",'Détail projets & dettes'!$B$5:$B$500,$A48) | U48: =S48+T48 | V48: =SUMIFS('Détail projets & dettes'!$M$5:$M$500,'Détail projets & dettes'!$A$5:$A$500,V$2,'Détail projets & dettes'!$J$5:$J$500,"O",'Détail projets & dettes'!$B$5:$B$500,$A48) | W48: =U48+V48
A49: TERASSON-PROJET | C49: BNI-TERASSON / Fonds projet NP | D49: Fonds projet (paiement CPI) | F49: =M49/$E$3 | G49: =O49/$E$3 | H49: =Q49/$E$3 | I49: =S49/$E$3 | J49: =U49/$E$3 | K49: =W49/$E$3 | M49: ='Position CI 30-09'!F29 | N49: =SUMIFS('Détail projets & dettes'!$M$5:$M$500,'Détail projets & dettes'!$A$5:$A$500,N$2,'Détail projets & dettes'!$J$5:$J$500,"O",'Détail projets & dettes'!$B$5:$B$500,$A49) | O49: =M49+N49 | P49: =SUMIFS('Détail projets & dettes'!$M$5:$M$500,'Détail projets & dettes'!$A$5:$A$500,P$2,'Détail projets & dettes'!$J$5:$J$500,"O",'Détail projets & dettes'!$B$5:$B$500,$A49) | Q49: =O49+P49 | R49: =SUMIFS('Détail projets & dettes'!$M$5:$M$500,'Détail projets & dettes'!$A$5:$A$500,R$2,'Détail projets & dettes'!$J$5:$J$500,"O",'Détail projets & dettes'!$B$5:$B$500,$A49) | S49: =Q49+R49 | T49: =SUMIFS('Détail projets & dettes'!$M$5:$M$500,'Détail projets & dettes'!$A$5:$A$500,T$2,'Détail projets & dettes'!$J$5:$J$500,"O",'Détail projets & dettes'!$B$5:$B$500,$A49) | U49: =S49+T49 | V49: =SUMIFS('Détail projets & dettes'!$M$5:$M$500,'Détail projets & dettes'!$A$5:$A$500,V$2,'Détail projets & dettes'!$J$5:$J$500,"O",'Détail projets & dettes'!$B$5:$B$500,$A49) | W49: =U49+V49
A50: SCO AO-BACIAGORACOMPTEBLOQUTVA | C50: BACI-AGORA/COMPTE BLOQU. TVA | D50: Compte réservé, non mobilisable | F50: =M50/$E$3 | G50: =O50/$E$3 | H50: =Q50/$E$3 | I50: =S50/$E$3 | J50: =U50/$E$3 | K50: =W50/$E$3 | M50: ='Position CI 30-09'!F30 | N50: =SUMIFS('Détail projets & dettes'!$M$5:$M$500,'Détail projets & dettes'!$A$5:$A$500,N$2,'Détail projets & dettes'!$J$5:$J$500,"O",'Détail projets & dettes'!$B$5:$B$500,$A50) | O50: =M50+N50 | P50: =SUMIFS('Détail projets & dettes'!$M$5:$M$500,'Détail projets & dettes'!$A$5:$A$500,P$2,'Détail projets & dettes'!$J$5:$J$500,"O",'Détail projets & dettes'!$B$5:$B$500,$A50) | Q50: =O50+P50 | R50: =SUMIFS('Détail projets & dettes'!$M$5:$M$500,'Détail projets & dettes'!$A$5:$A$500,R$2,'Détail projets & dettes'!$J$5:$J$500,"O",'Détail projets & dettes'!$B$5:$B$500,$A50) | S50: =Q50+R50 | T50: =SUMIFS('Détail projets & dettes'!$M$5:$M$500,'Détail projets & dettes'!$A$5:$A$500,T$2,'Détail projets & dettes'!$J$5:$J$500,"O",'Détail projets & dettes'!$B$5:$B$500,$A50) | U50: =S50+T50 | V50: =SUMIFS('Détail projets & dettes'!$M$5:$M$500,'Détail projets & dettes'!$A$5:$A$500,V$2,'Détail projets & dettes'!$J$5:$J$500,"O",'Détail projets & dettes'!$B$5:$B$500,$A50) | W50: =U50+V50
C51: TOTAL COMPTES DÉDIÉS | F51: =SUM(F47:F50) | G51: =SUM(G47:G50) | H51: =SUM(H47:H50) | I51: =SUM(I47:I50) | J51: =SUM(J47:J50) | K51: =SUM(K47:K50) | M51: =SUM(M47:M50) | N51: =SUM(N47:N50) | O51: =SUM(O47:O50) | P51: =SUM(P47:P50) | Q51: =SUM(Q47:Q50) | R51: =SUM(R47:R50) | S51: =SUM(S47:S50) | T51: =SUM(T47:T50) | ... W51: =SUM(W47:W50)
C52: TOTAL GÉNÉRAL CÔTE D'IVOIRE | F52: =F44+F51 | G52: =G44+G51 | H52: =H44+H51 | I52: =I44+I51 | J52: =J44+J51 | K52: =K44+K51 | M52: =M44+M51 | N52: =N44+N51 | O52: =O44+O51 | P52: =P44+P51 | Q52: =Q44+Q51 | R52: =R44+R51 | S52: =S44+S51 | T52: =T44+T51 | ... W52: =W44+W51
C54: Comptes indisponibles – pour information (hors position et hors totaux)
A55: FIRST | C55: STANBIC-FIRST _ Debt Service | D55: DSR/Augmentation/LL/Disbursment | F55: =M55/$E$3 | G55: =O55/$E$3 | H55: =Q55/$E$3 | I55: =S55/$E$3 | J55: =U55/$E$3 | K55: =W55/$E$3 | M55: ='Position CI 30-09'!F35 | O55: =M55 | Q55: =O55 | S55: =Q55 | U55: =S55 | W55: =U55
A56: FIRST | C56: STANBIC-FIRST_LL | D56: DSR/Augmentation/LL/Disbursment | F56: =M56/$E$3 | G56: =O56/$E$3 | H56: =Q56/$E$3 | I56: =S56/$E$3 | J56: =U56/$E$3 | K56: =W56/$E$3 | M56: ='Position CI 30-09'!F36 | O56: =M56 | Q56: =O56 | S56: =Q56 | U56: =S56 | W56: =U56
A57: FIRST | C57: STANBIC-FIRST_Disbursement | D57: DSR/Augmentation/LL/Disbursment | F57: =M57/$E$3 | G57: =O57/$E$3 | H57: =Q57/$E$3 | I57: =S57/$E$3 | J57: =U57/$E$3 | K57: =W57/$E$3 | M57: ='Position CI 30-09'!F37 | O57: =M57 | Q57: =O57 | S57: =Q57 | U57: =S57 | W57: =U57
A58: RIVIERA | C58: BNI-RIVIERA(Augmentation) | D58: DSR/Augmentation/LL/Disbursment | F58: =M58/$E$3 | G58: =O58/$E$3 | H58: =Q58/$E$3 | I58: =S58/$E$3 | J58: =U58/$E$3 | K58: =W58/$E$3 | M58: ='Position CI 30-09'!F38 | O58: =M58 | Q58: =O58 | S58: =Q58 | U58: =S58 | W58: =U58
A59: RIVIERA | C59: BNI-RIVIERA(DSRA) / Placement | D59: DSR/Augmentation/LL/Disbursment | F59: =M59/$E$3 | G59: =O59/$E$3 | H59: =Q59/$E$3 | I59: =S59/$E$3 | J59: =U59/$E$3 | K59: =W59/$E$3 | M59: ='Position CI 30-09'!F39 | O59: =M59 | Q59: =O59 | S59: =Q59 | U59: =S59 | W59: =U59
C60: Indisponibles : soldes inchangés sur S1 à S5, non mobilisables pour les paiements.
C62: SYNTHÈSE DES BESOINS PAR SEMAINE
C63: Flux de fonctionnement (frais de structure) | G63: =N63/$E$3 | H63: =P63/$E$3 | I63: =R63/$E$3 | J63: =T63/$E$3 | K63: =V63/$E$3 | N63: =SUMIFS('Détail fonctionnement'!$J$5:$J$505,'Détail fonctionnement'!$A$5:$A$505,N$2,'Détail fonctionnement'!$G$5:$G$505,"O") | P63: =SUMIFS('Détail fonctionnement'!$J$5:$J$505,'Détail fonctionnement'!$A$5:$A$505,P$2,'Détail fonctionnement'!$G$5:$G$505,"O") | R63: =SUMIFS('Détail fonctionnement'!$J$5:$J$505,'Détail fonctionnement'!$A$5:$A$505,R$2,'Détail fonctionnement'!$G$5:$G$505,"O") | T63: =SUMIFS('Détail fonctionnement'!$J$5:$J$505,'Détail fonctionnement'!$A$5:$A$505,T$2,'Détail fonctionnement'!$G$5:$G$505,"O") | V63: =SUMIFS('Détail fonctionnement'!$J$5:$J$505,'Détail fonctionnement'!$A$5:$A$505,V$2,'Détail fonctionnement'!$G$5:$G$505,"O")
C64: Flux projets et dettes (comptes dédiés) | G64: =N64/$E$3 | H64: =P64/$E$3 | I64: =R64/$E$3 | J64: =T64/$E$3 | K64: =V64/$E$3 | N64: =SUMIFS('Détail projets & dettes'!$M$5:$M$500,'Détail projets & dettes'!$A$5:$A$500,N$2,'Détail projets & dettes'!$J$5:$J$500,"O") | P64: =SUMIFS('Détail projets & dettes'!$M$5:$M$500,'Détail projets & dettes'!$A$5:$A$500,P$2,'Détail projets & dettes'!$J$5:$J$500,"O") | R64: =SUMIFS('Détail projets & dettes'!$M$5:$M$500,'Détail projets & dettes'!$A$5:$A$500,R$2,'Détail projets & dettes'!$J$5:$J$500,"O") | T64: =SUMIFS('Détail projets & dettes'!$M$5:$M$500,'Détail projets & dettes'!$A$5:$A$500,T$2,'Détail projets & dettes'!$J$5:$J$500,"O") | V64: =SUMIFS('Détail projets & dettes'!$M$5:$M$500,'Détail projets & dettes'!$A$5:$A$500,V$2,'Détail projets & dettes'!$J$5:$J$500,"O")
C65: Total des flux de la semaine | G65: =N65/$E$3 | H65: =P65/$E$3 | I65: =R65/$E$3 | J65: =T65/$E$3 | K65: =V65/$E$3 | N65: =N63+N64 | P65: =P63+P64 | R65: =R63+R64 | T65: =T63+T64 | V65: =V63+V64
C66: Besoin de trésorerie (–) ou Surplus de trésorerie (+) – comptes de sociétés | G66: =O66/$E$3 | H66: =Q66/$E$3 | I66: =S66/$E$3 | J66: =U66/$E$3 | K66: =W66/$E$3 | O66: =O44 | Q66: =Q44 | S66: =S44 | U66: =U44 | W66: =W44
C67: dont PICI | G67: =O67/$E$3 | H67: =Q67/$E$3 | I67: =S67/$E$3 | J67: =U67/$E$3 | K67: =W67/$E$3 | O67: =O11 | Q67: =Q11 | S67: =S11 | U67: =U11 | W67: =W11
C68: dont FIRST | G68: =O68/$E$3 | H68: =Q68/$E$3 | I68: =S68/$E$3 | J68: =U68/$E$3 | K68: =W68/$E$3 | O68: =O15 | Q68: =Q15 | S68: =S15 | U68: =U15 | W68: =W15
C69: Besoin de trésorerie (–) ou Surplus de trésorerie (+) – comptes dédiés | G69: =O69/$E$3 | H69: =Q69/$E$3 | I69: =S69/$E$3 | J69: =U69/$E$3 | K69: =W69/$E$3 | O69: =O51 | Q69: =Q51 | S69: =S51 | U69: =U51 | W69: =W51
C70: dont RIVIERA | G70: =O70/$E$3 | H70: =Q70/$E$3 | I70: =S70/$E$3 | J70: =U70/$E$3 | K70: =W70/$E$3 | O70: =O47+O48 | Q70: =Q47+Q48 | S70: =S47+S48 | U70: =U47+U48 | W70: =W47+W48
C71: dont TERASSON | G71: =O71/$E$3 | H71: =Q71/$E$3 | I71: =S71/$E$3 | J71: =U71/$E$3 | K71: =W71/$E$3 | O71: =O49 | Q71: =Q49 | S71: =S49 | U71: =U49 | W71: =W49
C73: Prévisions de décaissements et encaissements
A74: FRAIS DE STRUCTURES
B75: Semaine | C75: Entité | D75: Nature de transaction | F75: Montant prév. € | G75: Montant réel € | H75: Écart € | M75: Montant prév. FCFA | N75: Montant réel FCFA | O75: Écart FCFA | P75: Commentaires sur les écarts
C76: S1 : semaine du 05/10 au 11/10 (y compris antériorités)
B77: S1 | C77: PICI | D77: FOURNISSEURS - FGX | F77: =M77/$E$3 | G77: =IF(N77="","",N77/$E$3) | H77: =IF(G77="","",G77-F77) | M77: =SUMIFS('Détail fonctionnement'!$J$5:$J$505,'Détail fonctionnement'!$A$5:$A$505,$B77,'Détail fonctionnement'!$G$5:$G$505,"O",'Détail fonctionnement'!$B$5:$B$505,$C77,'Détail fonctionnement'!$C$5:$C$505,$D77) | O77: =IF(N77="","",N77-M77)
B78: S1 | C78: PICI | D78: IMPÔTS ET TAXES | F78: =M78/$E$3 | G78: =IF(N78="","",N78/$E$3) | H78: =IF(G78="","",G78-F78) | M78: =SUMIFS('Détail fonctionnement'!$J$5:$J$505,'Détail fonctionnement'!$A$5:$A$505,$B78,'Détail fonctionnement'!$G$5:$G$505,"O",'Détail fonctionnement'!$B$5:$B$505,$C78,'Détail fonctionnement'!$C$5:$C$505,$D78) | O78: =IF(N78="","",N78-M78)
B79: S1 | C79: PICI | D79: CHARGES SOCIALES | F79: =M79/$E$3 | G79: =IF(N79="","",N79/$E$3) | H79: =IF(G79="","",G79-F79) | M79: =SUMIFS('Détail fonctionnement'!$J$5:$J$505,'Détail fonctionnement'!$A$5:$A$505,$B79,'Détail fonctionnement'!$G$5:$G$505,"O",'Détail fonctionnement'!$B$5:$B$505,$C79,'Détail fonctionnement'!$C$5:$C$505,$D79) | O79: =IF(N79="","",N79-M79)
B80: S1 | C80: FIRST | D80: FOURNISSEURS - FGX | F80: =M80/$E$3 | G80: =IF(N80="","",N80/$E$3) | H80: =IF(G80="","",G80-F80) | M80: =SUMIFS('Détail fonctionnement'!$J$5:$J$505,'Détail fonctionnement'!$A$5:$A$505,$B80,'Détail fonctionnement'!$G$5:$G$505,"O",'Détail fonctionnement'!$B$5:$B$505,$C80,'Détail fonctionnement'!$C$5:$C$505,$D80) | O80: =IF(N80="","",N80-M80)
B81: S1 | C81: FIRST | D81: IMPÔTS ET TAXES | F81: =M81/$E$3 | G81: =IF(N81="","",N81/$E$3) | H81: =IF(G81="","",G81-F81) | M81: =SUMIFS('Détail fonctionnement'!$J$5:$J$505,'Détail fonctionnement'!$A$5:$A$505,$B81,'Détail fonctionnement'!$G$5:$G$505,"O",'Détail fonctionnement'!$B$5:$B$505,$C81,'Détail fonctionnement'!$C$5:$C$505,$D81) | O81: =IF(N81="","",N81-M81)
B82: S1 | C82: FIRST | D82: REMBOURSEMENT DE PRÊTS | F82: =M82/$E$3 | G82: =IF(N82="","",N82/$E$3) | H82: =IF(G82="","",G82-F82) | M82: =SUMIFS('Détail fonctionnement'!$J$5:$J$505,'Détail fonctionnement'!$A$5:$A$505,$B82,'Détail fonctionnement'!$G$5:$G$505,"O",'Détail fonctionnement'!$B$5:$B$505,$C82,'Détail fonctionnement'!$C$5:$C$505,$D82) | O82: =IF(N82="","",N82-M82)
B83: S1 | C83: TERASSON | D83: FOURNISSEURS - FGX | F83: =M83/$E$3 | G83: =IF(N83="","",N83/$E$3) | H83: =IF(G83="","",G83-F83) | M83: =SUMIFS('Détail fonctionnement'!$J$5:$J$505,'Détail fonctionnement'!$A$5:$A$505,$B83,'Détail fonctionnement'!$G$5:$G$505,"O",'Détail fonctionnement'!$B$5:$B$505,$C83,'Détail fonctionnement'!$C$5:$C$505,$D83) | O83: =IF(N83="","",N83-M83)
B84: S1 | C84: TERASSON | D84: IMPÔTS ET TAXES | F84: =M84/$E$3 | G84: =IF(N84="","",N84/$E$3) | H84: =IF(G84="","",G84-F84) | M84: =SUMIFS('Détail fonctionnement'!$J$5:$J$505,'Détail fonctionnement'!$A$5:$A$505,$B84,'Détail fonctionnement'!$G$5:$G$505,"O",'Détail fonctionnement'!$B$5:$B$505,$C84,'Détail fonctionnement'!$C$5:$C$505,$D84) | O84: =IF(N84="","",N84-M84)
B85: S1 | C85: RIVIERA | D85: FOURNISSEURS - FGX | F85: =M85/$E$3 | G85: =IF(N85="","",N85/$E$3) | H85: =IF(G85="","",G85-F85) | M85: =SUMIFS('Détail fonctionnement'!$J$5:$J$505,'Détail fonctionnement'!$A$5:$A$505,$B85,'Détail fonctionnement'!$G$5:$G$505,"O",'Détail fonctionnement'!$B$5:$B$505,$C85,'Détail fonctionnement'!$C$5:$C$505,$D85) | O85: =IF(N85="","",N85-M85)
B86: S1 | C86: RIVIERA | D86: IMPÔTS ET TAXES | F86: =M86/$E$3 | G86: =IF(N86="","",N86/$E$3) | H86: =IF(G86="","",G86-F86) | M86: =SUMIFS('Détail fonctionnement'!$J$5:$J$505,'Détail fonctionnement'!$A$5:$A$505,$B86,'Détail fonctionnement'!$G$5:$G$505,"O",'Détail fonctionnement'!$B$5:$B$505,$C86,'Détail fonctionnement'!$C$5:$C$505,$D86) | O86: =IF(N86="","",N86-M86)
B87: S1 | C87: RIVIERA | D87: CHARGES SOCIALES | F87: =M87/$E$3 | G87: =IF(N87="","",N87/$E$3) | H87: =IF(G87="","",G87-F87) | M87: =SUMIFS('Détail fonctionnement'!$J$5:$J$505,'Détail fonctionnement'!$A$5:$A$505,$B87,'Détail fonctionnement'!$G$5:$G$505,"O",'Détail fonctionnement'!$B$5:$B$505,$C87,'Détail fonctionnement'!$C$5:$C$505,$D87) | O87: =IF(N87="","",N87-M87)
B88: S1 | C88: SCO AO | D88: FOURNISSEURS - FGX | F88: =M88/$E$3 | G88: =IF(N88="","",N88/$E$3) | H88: =IF(G88="","",G88-F88) | M88: =SUMIFS('Détail fonctionnement'!$J$5:$J$505,'Détail fonctionnement'!$A$5:$A$505,$B88,'Détail fonctionnement'!$G$5:$G$505,"O",'Détail fonctionnement'!$B$5:$B$505,$C88,'Détail fonctionnement'!$C$5:$C$505,$D88) | O88: =IF(N88="","",N88-M88)
... B101: S1 | C101: RHD CI | D101: CHARGES SOCIALES | F101: =M101/$E$3 | G101: =IF(N101="","",N101/$E$3) | H101: =IF(G101="","",G101-F101) | M101: =SUMIFS('Détail fonctionnement'!$J$5:$J$505,'Détail fonctionnement'!$A$5:$A$505,$B101,'Détail fonctionnement'!$G$5:$G$505,"O",'Détail fonctionnement'!$B$5:$B$505,$C101,'Détail fonctionnement'!$C$5:$C$505,$D101) | O101: =IF(N101="","",N101-M101)
C102: Total S1 | F102: =SUM(F77:F101) | G102: =SUM(G77:G101) | H102: =SUM(H77:H101) | M102: =SUM(M77:M101) | N102: =SUM(N77:N101) | O102: =SUM(O77:O101)
C104: S2 : semaine du 12/10 au 18/10
B105: S2 | C105: PICI | D105: IMPÔTS ET TAXES | F105: =M105/$E$3 | G105: =IF(N105="","",N105/$E$3) | H105: =IF(G105="","",G105-F105) | M105: =SUMIFS('Détail fonctionnement'!$J$5:$J$505,'Détail fonctionnement'!$A$5:$A$505,$B105,'Détail fonctionnement'!$G$5:$G$505,"O",'Détail fonctionnement'!$B$5:$B$505,$C105,'Détail fonctionnement'!$C$5:$C$505,$D105) | O105: =IF(N105="","",N105-M105)
B106: S2 | C106: PICI | D106: CHARGES SOCIALES | F106: =M106/$E$3 | G106: =IF(N106="","",N106/$E$3) | H106: =IF(G106="","",G106-F106) | M106: =SUMIFS('Détail fonctionnement'!$J$5:$J$505,'Détail fonctionnement'!$A$5:$A$505,$B106,'Détail fonctionnement'!$G$5:$G$505,"O",'Détail fonctionnement'!$B$5:$B$505,$C106,'Détail fonctionnement'!$C$5:$C$505,$D106) | O106: =IF(N106="","",N106-M106)
B107: S2 | C107: FIRST | D107: FOURNISSEURS - FGX | F107: =M107/$E$3 | G107: =IF(N107="","",N107/$E$3) | H107: =IF(G107="","",G107-F107) | M107: =SUMIFS('Détail fonctionnement'!$J$5:$J$505,'Détail fonctionnement'!$A$5:$A$505,$B107,'Détail fonctionnement'!$G$5:$G$505,"O",'Détail fonctionnement'!$B$5:$B$505,$C107,'Détail fonctionnement'!$C$5:$C$505,$D107) | O107: =IF(N107="","",N107-M107)
B108: S2 | C108: FIRST | D108: ENCAISSEMENTS | F108: =M108/$E$3 | G108: =IF(N108="","",N108/$E$3) | H108: =IF(G108="","",G108-F108) | M108: =SUMIFS('Détail fonctionnement'!$J$5:$J$505,'Détail fonctionnement'!$A$5:$A$505,$B108,'Détail fonctionnement'!$G$5:$G$505,"O",'Détail fonctionnement'!$B$5:$B$505,$C108,'Détail fonctionnement'!$C$5:$C$505,$D108) | O108: =IF(N108="","",N108-M108)
B109: S2 | C109: RIVIERA | D109: IMPÔTS ET TAXES | F109: =M109/$E$3 | G109: =IF(N109="","",N109/$E$3) | H109: =IF(G109="","",G109-F109) | M109: =SUMIFS('Détail fonctionnement'!$J$5:$J$505,'Détail fonctionnement'!$A$5:$A$505,$B109,'Détail fonctionnement'!$G$5:$G$505,"O",'Détail fonctionnement'!$B$5:$B$505,$C109,'Détail fonctionnement'!$C$5:$C$505,$D109) | O109: =IF(N109="","",N109-M109)
B110: S2 | C110: RIVIERA | D110: CHARGES SOCIALES | F110: =M110/$E$3 | G110: =IF(N110="","",N110/$E$3) | H110: =IF(G110="","",G110-F110) | M110: =SUMIFS('Détail fonctionnement'!$J$5:$J$505,'Détail fonctionnement'!$A$5:$A$505,$B110,'Détail fonctionnement'!$G$5:$G$505,"O",'Détail fonctionnement'!$B$5:$B$505,$C110,'Détail fonctionnement'!$C$5:$C$505,$D110) | O110: =IF(N110="","",N110-M110)
B111: S2 | C111: SCO AO | D111: FOURNISSEURS - FGX | F111: =M111/$E$3 | G111: =IF(N111="","",N111/$E$3) | H111: =IF(G111="","",G111-F111) | M111: =SUMIFS('Détail fonctionnement'!$J$5:$J$505,'Détail fonctionnement'!$A$5:$A$505,$B111,'Détail fonctionnement'!$G$5:$G$505,"O",'Détail fonctionnement'!$B$5:$B$505,$C111,'Détail fonctionnement'!$C$5:$C$505,$D111) | O111: =IF(N111="","",N111-M111)
B112: S2 | C112: SCO AO | D112: FOURNISSEURS - PROJET | F112: =M112/$E$3 | G112: =IF(N112="","",N112/$E$3) | H112: =IF(G112="","",G112-F112) | M112: =SUMIFS('Détail fonctionnement'!$J$5:$J$505,'Détail fonctionnement'!$A$5:$A$505,$B112,'Détail fonctionnement'!$G$5:$G$505,"O",'Détail fonctionnement'!$B$5:$B$505,$C112,'Détail fonctionnement'!$C$5:$C$505,$D112) | O112: =IF(N112="","",N112-M112)
B113: S2 | C113: SCO AO | D113: CHARGES SOCIALES | F113: =M113/$E$3 | G113: =IF(N113="","",N113/$E$3) | H113: =IF(G113="","",G113-F113) | M113: =SUMIFS('Détail fonctionnement'!$J$5:$J$505,'Détail fonctionnement'!$A$5:$A$505,$B113,'Détail fonctionnement'!$G$5:$G$505,"O",'Détail fonctionnement'!$B$5:$B$505,$C113,'Détail fonctionnement'!$C$5:$C$505,$D113) | O113: =IF(N113="","",N113-M113)
B114: S2 | C114: SCO AO | D114: ENCAISSEMENTS | F114: =M114/$E$3 | G114: =IF(N114="","",N114/$E$3) | H114: =IF(G114="","",G114-F114) | M114: =SUMIFS('Détail fonctionnement'!$J$5:$J$505,'Détail fonctionnement'!$A$5:$A$505,$B114,'Détail fonctionnement'!$G$5:$G$505,"O",'Détail fonctionnement'!$B$5:$B$505,$C114,'Détail fonctionnement'!$C$5:$C$505,$D114) | O114: =IF(N114="","",N114-M114)
B115: S2 | C115: FINAFRICA | D115: IMPÔTS ET TAXES | F115: =M115/$E$3 | G115: =IF(N115="","",N115/$E$3) | H115: =IF(G115="","",G115-F115) | M115: =SUMIFS('Détail fonctionnement'!$J$5:$J$505,'Détail fonctionnement'!$A$5:$A$505,$B115,'Détail fonctionnement'!$G$5:$G$505,"O",'Détail fonctionnement'!$B$5:$B$505,$C115,'Détail fonctionnement'!$C$5:$C$505,$D115) | O115: =IF(N115="","",N115-M115)
B116: S2 | C116: FINAFRICA | D116: CHARGES SOCIALES | F116: =M116/$E$3 | G116: =IF(N116="","",N116/$E$3) | H116: =IF(G116="","",G116-F116) | M116: =SUMIFS('Détail fonctionnement'!$J$5:$J$505,'Détail fonctionnement'!$A$5:$A$505,$B116,'Détail fonctionnement'!$G$5:$G$505,"O",'Détail fonctionnement'!$B$5:$B$505,$C116,'Détail fonctionnement'!$C$5:$C$505,$D116) | O116: =IF(N116="","",N116-M116)
... B120: S2 | C120: RHD CI | D120: CHARGES SOCIALES | F120: =M120/$E$3 | G120: =IF(N120="","",N120/$E$3) | H120: =IF(G120="","",G120-F120) | M120: =SUMIFS('Détail fonctionnement'!$J$5:$J$505,'Détail fonctionnement'!$A$5:$A$505,$B120,'Détail fonctionnement'!$G$5:$G$505,"O",'Détail fonctionnement'!$B$5:$B$505,$C120,'Détail fonctionnement'!$C$5:$C$505,$D120) | O120: =IF(N120="","",N120-M120)
C121: Total S2 | F121: =SUM(F105:F120) | G121: =SUM(G105:G120) | H121: =SUM(H105:H120) | M121: =SUM(M105:M120) | N121: =SUM(N105:N120) | O121: =SUM(O105:O120)
C123: S3 : semaine du 19/10 au 25/10
...

Sheet Équilibrage S1
A1: Équilibrage et affectation des paiements – S1 (05/10 au 11/10/2026)
A2: Paiements : liens vers les feuilles de détail (S1, Retenu = O). Soldes : liens vers la position CI. Nivellements : tableau des virements ci-dessous (modifiable).
A4: Opérations à effectuer | B4: Paiement via | AB4: Observations
B5: TERASSON | E5: PICI | H5: SCI FIRST | J5: RIVIERA PARK | M5: SCO AO | R5: IMMONEUF | U5: FINAFRICA | W5: INFI | X5: ODALYS CI | Y5: AB CENTER | AA5: RHD CI
B6: BNI fonds projet | C6: SG | D6: ECO | E6: STB | F6: SG | G6: ECO | H6: STB | I6: SG | J6: BNI fonds projet | K6: BNI courant | L6: SG | M6: BACI Projet | N6: BACI courant | O6: BOA | P6: BACI AGORA | Q6: ECO | R6: SG | S6: BACI | T6: ECO | U6: SG | V6: ECO | W6: SIB | X6: SG | Y6: ECO | Z6: SG | AA6: payé par PICI
A7: NIVELLEMENT VIA PICI | B7: =SUMIFS($H$25:$H$55,$A$25:$A$55,"NIVELLEMENT VIA PICI",$E$25:$E$55,"TERASSON – BNI fonds projet")-SUMIFS($H$25:$H$55,$A$25:$A$55,"NIVELLEMENT VIA PICI",$C$25:$C$55,"TERASSON – BNI fonds projet") | C7: =SUMIFS($H$25:$H$55,$A$25:$A$55,"NIVELLEMENT VIA PICI",$E$25:$E$55,"TERASSON – SG")-SUMIFS($H$25:$H$55,$A$25:$A$55,"NIVELLEMENT VIA PICI",$C$25:$C$55,"TERASSON – SG") | D7: =SUMIFS($H$25:$H$55,$A$25:$A$55,"NIVELLEMENT VIA PICI",$E$25:$E$55,"TERASSON – ECO")-SUMIFS($H$25:$H$55,$A$25:$A$55,"NIVELLEMENT VIA PICI",$C$25:$C$55,"TERASSON – ECO") | E7: =SUMIFS($H$25:$H$55,$A$25:$A$55,"NIVELLEMENT VIA PICI",$E$25:$E$55,"PICI – STB")-SUMIFS($H$25:$H$55,$A$25:$A$55,"NIVELLEMENT VIA PICI",$C$25:$C$55,"PICI – STB") | F7: =SUMIFS($H$25:$H$55,$A$25:$A$55,"NIVELLEMENT VIA PICI",$E$25:$E$55,"PICI – SG")-SUMIFS($H$25:$H$55,$A$25:$A$55,"NIVELLEMENT VIA PICI",$C$25:$C$55,"PICI – SG") | G7: =SUMIFS($H$25:$H$55,$A$25:$A$55,"NIVELLEMENT VIA PICI",$E$25:$E$55,"PICI – ECO")-SUMIFS($H$25:$H$55,$A$25:$A$55,"NIVELLEMENT VIA PICI",$C$25:$C$55,"PICI – ECO") | H7: =SUMIFS($H$25:$H$55,$A$25:$A$55,"NIVELLEMENT VIA PICI",$E$25:$E$55,"SCI FIRST – STB")-SUMIFS($H$25:$H$55,$A$25:$A$55,"NIVELLEMENT VIA PICI",$C$25:$C$55,"SCI FIRST – STB") | I7: =SUMIFS($H$25:$H$55,$A$25:$A$55,"NIVELLEMENT VIA PICI",$E$25:$E$55,"SCI FIRST – SG")-SUMIFS($H$25:$H$55,$A$25:$A$55,"NIVELLEMENT VIA PICI",$C$25:$C$55,"SCI FIRST – SG") | J7: =SUMIFS($H$25:$H$55,$A$25:$A$55,"NIVELLEMENT VIA PICI",$E$25:$E$55,"RIVIERA PARK – BNI fonds projet")-SUMIFS($H$25:$H$55,$A$25:$A$55,"NIVELLEMENT VIA PICI",$C$25:$C$55,"RIVIERA PARK – BNI fonds projet") | K7: =SUMIFS($H$25:$H$55,$A$25:$A$55,"NIVELLEMENT VIA PICI",$E$25:$E$55,"RIVIERA PARK – BNI courant")-SUMIFS($H$25:$H$55,$A$25:$A$55,"NIVELLEMENT VIA PICI",$C$25:$C$55,"RIVIERA PARK – BNI courant") | L7: =SUMIFS($H$25:$H$55,$A$25:$A$55,"NIVELLEMENT VIA PICI",$E$25:$E$55,"RIVIERA PARK – SG")-SUMIFS($H$25:$H$55,$A$25:$A$55,"NIVELLEMENT VIA PICI",$C$25:$C$55,"RIVIERA PARK – SG") | M7: =SUMIFS($H$25:$H$55,$A$25:$A$55,"NIVELLEMENT VIA PICI",$E$25:$E$55,"SCO AO – BACI Projet")-SUMIFS($H$25:$H$55,$A$25:$A$55,"NIVELLEMENT VIA PICI",$C$25:$C$55,"SCO AO – BACI Projet") | N7: =SUMIFS($H$25:$H$55,$A$25:$A$55,"NIVELLEMENT VIA PICI",$E$25:$E$55,"SCO AO – BACI courant")-SUMIFS($H$25:$H$55,$A$25:$A$55,"NIVELLEMENT VIA PICI",$C$25:$C$55,"SCO AO – BACI courant") | O7: =SUMIFS($H$25:$H$55,$A$25:$A$55,"NIVELLEMENT VIA PICI",$E$25:$E$55,"SCO AO – BOA")-SUMIFS($H$25:$H$55,$A$25:$A$55,"NIVELLEMENT VIA PICI",$C$25:$C$55,"SCO AO – BOA") | P7: =SUMIFS($H$25:$H$55,$A$25:$A$55,"NIVELLEMENT VIA PICI",$E$25:$E$55,"SCO AO – BACI AGORA")-SUMIFS($H$25:$H$55,$A$25:$A$55,"NIVELLEMENT VIA PICI",$C$25:$C$55,"SCO AO – BACI AGORA") | Q7: =SUMIFS($H$25:$H$55,$A$25:$A$55,"NIVELLEMENT VIA PICI",$E$25:$E$55,"SCO AO – ECO")-SUMIFS($H$25:$H$55,$A$25:$A$55,"NIVELLEMENT VIA PICI",$C$25:$C$55,"SCO AO – ECO") | R7: =SUMIFS($H$25:$H$55,$A$25:$A$55,"NIVELLEMENT VIA PICI",$E$25:$E$55,"IMMONEUF – SG")-SUMIFS($H$25:$H$55,$A$25:$A$55,"NIVELLEMENT VIA PICI",$C$25:$C$55,"IMMONEUF – SG") | S7: =SUMIFS($H$25:$H$55,$A$25:$A$55,"NIVELLEMENT VIA PICI",$E$25:$E$55,"IMMONEUF – BACI")-SUMIFS($H$25:$H$55,$A$25:$A$55,"NIVELLEMENT VIA PICI",$C$25:$C$55,"IMMONEUF – BACI") | T7: =SUMIFS($H$25:$H$55,$A$25:$A$55,"NIVELLEMENT VIA PICI",$E$25:$E$55,"IMMONEUF – ECO")-SUMIFS($H$25:$H$55,$A$25:$A$55,"NIVELLEMENT VIA PICI",$C$25:$C$55,"IMMONEUF – ECO") | U7: =SUMIFS($H$25:$H$55,$A$25:$A$55,"NIVELLEMENT VIA PICI",$E$25:$E$55,"FINAFRICA – SG")-SUMIFS($H$25:$H$55,$A$25:$A$55,"NIVELLEMENT VIA PICI",$C$25:$C$55,"FINAFRICA – SG") | V7: =SUMIFS($H$25:$H$55,$A$25:$A$55,"NIVELLEMENT VIA PICI",$E$25:$E$55,"FINAFRICA – ECO")-SUMIFS($H$25:$H$55,$A$25:$A$55,"NIVELLEMENT VIA PICI",$C$25:$C$55,"FINAFRICA – ECO") | W7: =SUMIFS($H$25:$H$55,$A$25:$A$55,"NIVELLEMENT VIA PICI",$E$25:$E$55,"INFI – SIB")-SUMIFS($H$25:$H$55,$A$25:$A$55,"NIVELLEMENT VIA PICI",$C$25:$C$55,"INFI – SIB") | X7: =SUMIFS($H$25:$H$55,$A$25:$A$55,"NIVELLEMENT VIA PICI",$E$25:$E$55,"ODALYS CI – SG")-SUMIFS($H$25:$H$55,$A$25:$A$55,"NIVELLEMENT VIA PICI",$C$25:$C$55,"ODALYS CI – SG") | Y7: =SUMIFS($H$25:$H$55,$A$25:$A$55,"NIVELLEMENT VIA PICI",$E$25:$E$55,"AB CENTER – ECO")-SUMIFS($H$25:$H$55,$A$25:$A$55,"NIVELLEMENT VIA PICI",$C$25:$C$55,"AB CENTER – ECO") | Z7: =SUMIFS($H$25:$H$55,$A$25:$A$55,"NIVELLEMENT VIA PICI",$E$25:$E$55,"AB CENTER – SG")-SUMIFS($H$25:$H$55,$A$25:$A$55,"NIVELLEMENT VIA PICI",$C$25:$C$55,"AB CENTER – SG") | AA7: =SUMIFS($H$25:$H$55,$A$25:$A$55,"NIVELLEMENT VIA PICI",$E$25:$E$55,"RHD CI – payé par PICI")-SUMIFS($H$25:$H$55,$A$25:$A$55,"NIVELLEMENT VIA PICI",$C$25:$C$55,"RHD CI – payé par PICI") | AB7: Excédents PICI puis FIRST vers les sociétés en déficit : impôts, cotisations et salaires d'abord, fournisseurs ensuite
A8: AUTRES NIVELLEMENTS | B8: =SUMIFS($H$25:$H$55,$A$25:$A$55,"AUTRES NIVELLEMENTS",$E$25:$E$55,"TERASSON – BNI fonds projet")-SUMIFS($H$25:$H$55,$A$25:$A$55,"AUTRES NIVELLEMENTS",$C$25:$C$55,"TERASSON – BNI fonds projet") | C8: =SUMIFS($H$25:$H$55,$A$25:$A$55,"AUTRES NIVELLEMENTS",$E$25:$E$55,"TERASSON – SG")-SUMIFS($H$25:$H$55,$A$25:$A$55,"AUTRES NIVELLEMENTS",$C$25:$C$55,"TERASSON – SG") | D8: =SUMIFS($H$25:$H$55,$A$25:$A$55,"AUTRES NIVELLEMENTS",$E$25:$E$55,"TERASSON – ECO")-SUMIFS($H$25:$H$55,$A$25:$A$55,"AUTRES NIVELLEMENTS",$C$25:$C$55,"TERASSON – ECO") | E8: =SUMIFS($H$25:$H$55,$A$25:$A$55,"AUTRES NIVELLEMENTS",$E$25:$E$55,"PICI – STB")-SUMIFS($H$25:$H$55,$A$25:$A$55,"AUTRES NIVELLEMENTS",$C$25:$C$55,"PICI – STB") | F8: =SUMIFS($H$25:$H$55,$A$25:$A$55,"AUTRES NIVELLEMENTS",$E$25:$E$55,"PICI – SG")-SUMIFS($H$25:$H$55,$A$25:$A$55,"AUTRES NIVELLEMENTS",$C$25:$C$55,"PICI – SG") | G8: =SUMIFS($H$25:$H$55,$A$25:$A$55,"AUTRES NIVELLEMENTS",$E$25:$E$55,"PICI – ECO")-SUMIFS($H$25:$H$55,$A$25:$A$55,"AUTRES NIVELLEMENTS",$C$25:$C$55,"PICI – ECO") | H8: =SUMIFS($H$25:$H$55,$A$25:$A$55,"AUTRES NIVELLEMENTS",$E$25:$E$55,"SCI FIRST – STB")-SUMIFS($H$25:$H$55,$A$25:$A$55,"AUTRES NIVELLEMENTS",$C$25:$C$55,"SCI FIRST – STB") | I8: =SUMIFS($H$25:$H$55,$A$25:$A$55,"AUTRES NIVELLEMENTS",$E$25:$E$55,"SCI FIRST – SG")-SUMIFS($H$25:$H$55,$A$25:$A$55,"AUTRES NIVELLEMENTS",$C$25:$C$55,"SCI FIRST – SG") | J8: =SUMIFS($H$25:$H$55,$A$25:$A$55,"AUTRES NIVELLEMENTS",$E$25:$E$55,"RIVIERA PARK – BNI fonds projet")-SUMIFS($H$25:$H$55,$A$25:$A$55,"AUTRES NIVELLEMENTS",$C$25:$C$55,"RIVIERA PARK – BNI fonds projet") | K8: =SUMIFS($H$25:$H$55,$A$25:$A$55,"AUTRES NIVELLEMENTS",$E$25:$E$55,"RIVIERA PARK – BNI courant")-SUMIFS($H$25:$H$55,$A$25:$A$55,"AUTRES NIVELLEMENTS",$C$25:$C$55,"RIVIERA PARK – BNI courant") | L8: =SUMIFS($H$25:$H$55,$A$25:$A$55,"AUTRES NIVELLEMENTS",$E$25:$E$55,"RIVIERA PARK – SG")-SUMIFS($H$25:$H$55,$A$25:$A$55,"AUTRES NIVELLEMENTS",$C$25:$C$55,"RIVIERA PARK – SG") | M8: =SUMIFS($H$25:$H$55,$A$25:$A$55,"AUTRES NIVELLEMENTS",$E$25:$E$55,"SCO AO – BACI Projet")-SUMIFS($H$25:$H$55,$A$25:$A$55,"AUTRES NIVELLEMENTS",$C$25:$C$55,"SCO AO – BACI Projet") | N8: =SUMIFS($H$25:$H$55,$A$25:$A$55,"AUTRES NIVELLEMENTS",$E$25:$E$55,"SCO AO – BACI courant")-SUMIFS($H$25:$H$55,$A$25:$A$55,"AUTRES NIVELLEMENTS",$C$25:$C$55,"SCO AO – BACI courant") | O8: =SUMIFS($H$25:$H$55,$A$25:$A$55,"AUTRES NIVELLEMENTS",$E$25:$E$55,"SCO AO – BOA")-SUMIFS($H$25:$H$55,$A$25:$A$55,"AUTRES NIVELLEMENTS",$C$25:$C$55,"SCO AO – BOA") | P8: =SUMIFS($H$25:$H$55,$A$25:$A$55,"AUTRES NIVELLEMENTS",$E$25:$E$55,"SCO AO – BACI AGORA")-SUMIFS($H$25:$H$55,$A$25:$A$55,"AUTRES NIVELLEMENTS",$C$25:$C$55,"SCO AO – BACI AGORA") | Q8: =SUMIFS($H$25:$H$55,$A$25:$A$55,"AUTRES NIVELLEMENTS",$E$25:$E$55,"SCO AO – ECO")-SUMIFS($H$25:$H$55,$A$25:$A$55,"AUTRES NIVELLEMENTS",$C$25:$C$55,"SCO AO – ECO") | R8: =SUMIFS($H$25:$H$55,$A$25:$A$55,"AUTRES NIVELLEMENTS",$E$25:$E$55,"IMMONEUF – SG")-SUMIFS($H$25:$H$55,$A$25:$A$55,"AUTRES NIVELLEMENTS",$C$25:$C$55,"IMMONEUF – SG") | S8: =SUMIFS($H$25:$H$55,$A$25:$A$55,"AUTRES NIVELLEMENTS",$E$25:$E$55,"IMMONEUF – BACI")-SUMIFS($H$25:$H$55,$A$25:$A$55,"AUTRES NIVELLEMENTS",$C$25:$C$55,"IMMONEUF – BACI") | T8: =SUMIFS($H$25:$H$55,$A$25:$A$55,"AUTRES NIVELLEMENTS",$E$25:$E$55,"IMMONEUF – ECO")-SUMIFS($H$25:$H$55,$A$25:$A$55,"AUTRES NIVELLEMENTS",$C$25:$C$55,"IMMONEUF – ECO") | U8: =SUMIFS($H$25:$H$55,$A$25:$A$55,"AUTRES NIVELLEMENTS",$E$25:$E$55,"FINAFRICA – SG")-SUMIFS($H$25:$H$55,$A$25:$A$55,"AUTRES NIVELLEMENTS",$C$25:$C$55,"FINAFRICA – SG") | V8: =SUMIFS($H$25:$H$55,$A$25:$A$55,"AUTRES NIVELLEMENTS",$E$25:$E$55,"FINAFRICA – ECO")-SUMIFS($H$25:$H$55,$A$25:$A$55,"AUTRES NIVELLEMENTS",$C$25:$C$55,"FINAFRICA – ECO") | W8: =SUMIFS($H$25:$H$55,$A$25:$A$55,"AUTRES NIVELLEMENTS",$E$25:$E$55,"INFI – SIB")-SUMIFS($H$25:$H$55,$A$25:$A$55,"AUTRES NIVELLEMENTS",$C$25:$C$55,"INFI – SIB") | X8: =SUMIFS($H$25:$H$55,$A$25:$A$55,"AUTRES NIVELLEMENTS",$E$25:$E$55,"ODALYS CI – SG")-SUMIFS($H$25:$H$55,$A$25:$A$55,"AUTRES NIVELLEMENTS",$C$25:$C$55,"ODALYS CI – SG") | Y8: =SUMIFS($H$25:$H$55,$A$25:$A$55,"AUTRES NIVELLEMENTS",$E$25:$E$55,"AB CENTER – ECO")-SUMIFS($H$25:$H$55,$A$25:$A$55,"AUTRES NIVELLEMENTS",$C$25:$C$55,"AB CENTER – ECO") | Z8: =SUMIFS($H$25:$H$55,$A$25:$A$55,"AUTRES NIVELLEMENTS",$E$25:$E$55,"AB CENTER – SG")-SUMIFS($H$25:$H$55,$A$25:$A$55,"AUTRES NIVELLEMENTS",$C$25:$C$55,"AB CENTER – SG") | AA8: =SUMIFS($H$25:$H$55,$A$25:$A$55,"AUTRES NIVELLEMENTS",$E$25:$E$55,"RHD CI – payé par PICI")-SUMIFS($H$25:$H$55,$A$25:$A$55,"AUTRES NIVELLEMENTS",$C$25:$C$55,"RHD CI – payé par PICI") | AB8: Virements entre comptes d'une même entité (BNI-RIVIERA courant : sous réserve d'arbitrage)
A9: FOURNISSEURS-PROJETS | B9: =SUMIFS('Détail projets & dettes'!$M$5:$M$500,'Détail projets & dettes'!$A$5:$A$500,"S1",'Détail projets & dettes'!$B$5:$B$500,"TERASSON-PROJET",'Détail projets & dettes'!$J$5:$J$500,"O") | C9: =SUMIFS('Détail fonctionnement'!$J$5:$J$505,'Détail fonctionnement'!$A$5:$A$505,"S1",'Détail fonctionnement'!$B$5:$B$505,"TERASSON",'Détail fonctionnement'!$C$5:$C$505,"FOURNISSEURS - PROJET",'Détail fonctionnement'!$G$5:$G$505,"O") | E9: =SUMIFS('Détail fonctionnement'!$J$5:$J$505,'Détail fonctionnement'!$A$5:$A$505,"S1",'Détail fonctionnement'!$B$5:$B$505,"PICI",'Détail fonctionnement'!$C$5:$C$505,"FOURNISSEURS - PROJET",'Détail fonctionnement'!$G$5:$G$505,"O") | H9: =SUMIFS('Détail fonctionnement'!$J$5:$J$505,'Détail fonctionnement'!$A$5:$A$505,"S1",'Détail fonctionnement'!$B$5:$B$505,"FIRST",'Détail fonctionnement'!$C$5:$C$505,"FOURNISSEURS - PROJET",'Détail fonctionnement'!$G$5:$G$505,"O") | J9: =SUMIFS('Détail projets & dettes'!$M$5:$M$500,'Détail projets & dettes'!$A$5:$A$500,"S1",'Détail projets & dettes'!$B$5:$B$500,"RIVIERA-PROJET",'Détail projets & dettes'!$J$5:$J$500,"O") | L9: =SUMIFS('Détail fonctionnement'!$J$5:$J$505,'Détail fonctionnement'!$A$5:$A$505,"S1",'Détail fonctionnement'!$B$5:$B$505,"RIVIERA",'Détail fonctionnement'!$C$5:$C$505,"FOURNISSEURS - PROJET",'Détail fonctionnement'!$G$5:$G$505,"O") | M9: =SUMIFS('Détail fonctionnement'!$J$5:$J$505,'Détail fonctionnement'!$A$5:$A$505,"S1",'Détail fonctionnement'!$B$5:$B$505,"SCO AO",'Détail fonctionnement'!$C$5:$C$505,"FOURNISSEURS - PROJET",'Détail fonctionnement'!$G$5:$G$505,"O") | R9: =SUMIFS('Détail fonctionnement'!$J$5:$J$505,'Détail fonctionnement'!$A$5:$A$505,"S1",'Détail fonctionnement'!$B$5:$B$505,"IMMONEUF",'Détail fonctionnement'!$C$5:$C$505,"FOURNISSEURS - PROJET",'Détail fonctionnement'!$G$5:$G$505,"O") | U9: =SUMIFS('Détail fonctionnement'!$J$5:$J$505,'Détail fonctionnement'!$A$5:$A$505,"S1",'Détail fonctionnement'!$B$5:$B$505,"FINAFRICA",'Détail fonctionnement'!$C$5:$C$505,"FOURNISSEURS - PROJET",'Détail fonctionnement'!$G$5:$G$505,"O") | W9: =SUMIFS('Détail fonctionnement'!$J$5:$J$505,'Détail fonctionnement'!$A$5:$A$505,"S1",'Détail fonctionnement'!$B$5:$B$505,"INFI SOFT",'Détail fonctionnement'!$C$5:$C$505,"FOURNISSEURS - PROJET",'Détail fonctionnement'!$G$5:$G$505,"O") | X9: =SUMIFS('Détail fonctionnement'!$J$5:$J$505,'Détail fonctionnement'!$A$5:$A$505,"S1",'Détail fonctionnement'!$B$5:$B$505,"ODALYS CI",'Détail fonctionnement'!$C$5:$C$505,"FOURNISSEURS - PROJET",'Détail fonctionnement'!$G$5:$G$505,"O") | Y9: =SUMIFS('Détail fonctionnement'!$J$5:$J$505,'Détail fonctionnement'!$A$5:$A$505,"S1",'Détail fonctionnement'!$B$5:$B$505,"AB CENTER",'Détail fonctionnement'!$C$5:$C$505,"FOURNISSEURS - PROJET",'Détail fonctionnement'!$G$5:$G$505,"O") | AA9: =SUMIFS('Détail fonctionnement'!$J$5:$J$505,'Détail fonctionnement'!$A$5:$A$505,"S1",'Détail fonctionnement'!$B$5:$B$505,"RHD CI",'Détail fonctionnement'!$C$5:$C$505,"FOURNISSEURS - PROJET",'Détail fonctionnement'!$G$5:$G$505,"O") | AB9: Cash plans : comptes « Dédié paiement CPI » ; SCO AO : BACI-Projet
A10: FOURNISSEURS-FGX | C10: =SUMIFS('Détail fonctionnement'!$J$5:$J$505,'Détail fonctionnement'!$A$5:$A$505,"S1",'Détail fonctionnement'!$B$5:$B$505,"TERASSON",'Détail fonctionnement'!$C$5:$C$505,"FOURNISSEURS - FGX",'Détail fonctionnement'!$G$5:$G$505,"O") | E10: =SUMIFS('Détail fonctionnement'!$J$5:$J$505,'Détail fonctionnement'!$A$5:$A$505,"S1",'Détail fonctionnement'!$B$5:$B$505,"PICI",'Détail fonctionnement'!$C$5:$C$505,"FOURNISSEURS - FGX",'Détail fonctionnement'!$G$5:$G$505,"O") | H10: =SUMIFS('Détail fonctionnement'!$J$5:$J$505,'Détail fonctionnement'!$A$5:$A$505,"S1",'Détail fonctionnement'!$B$5:$B$505,"FIRST",'Détail fonctionnement'!$C$5:$C$505,"FOURNISSEURS - FGX",'Détail fonctionnement'!$G$5:$G$505,"O") | L10: =SUMIFS('Détail fonctionnement'!$J$5:$J$505,'Détail fonctionnement'!$A$5:$A$505,"S1",'Détail fonctionnement'!$B$5:$B$505,"RIVIERA",'Détail fonctionnement'!$C$5:$C$505,"FOURNISSEURS - FGX",'Détail fonctionnement'!$G$5:$G$505,"O") | N10: =SUMIFS('Détail fonctionnement'!$J$5:$J$505,'Détail fonctionnement'!$A$5:$A$505,"S1",'Détail fonctionnement'!$B$5:$B$505,"SCO AO",'Détail fonctionnement'!$C$5:$C$505,"FOURNISSEURS - FGX",'Détail fonctionnement'!$G$5:$G$505,"O") | R10: =SUMIFS('Détail fonctionnement'!$J$5:$J$505,'Détail fonctionnement'!$A$5:$A$505,"S1",'Détail fonctionnement'!$B$5:$B$505,"IMMONEUF",'Détail fonctionnement'!$C$5:$C$505,"FOURNISSEURS - FGX",'Détail fonctionnement'!$G$5:$G$505,"O") | U10: =SUMIFS('Détail fonctionnement'!$J$5:$J$505,'Détail fonctionnement'!$A$5:$A$505,"S1",'Détail fonctionnement'!$B$5:$B$505,"FINAFRICA",'Détail fonctionnement'!$C$5:$C$505,"FOURNISSEURS - FGX",'Détail fonctionnement'!$G$5:$G$505,"O") | W10: =SUMIFS('Détail fonctionnement'!$J$5:$J$505,'Détail fonctionnement'!$A$5:$A$505,"S1",'Détail fonctionnement'!$B$5:$B$505,"INFI SOFT",'Détail fonctionnement'!$C$5:$C$505,"FOURNISSEURS - FGX",'Détail fonctionnement'!$G$5:$G$505,"O") | X10: =SUMIFS('Détail fonctionnement'!$J$5:$J$505,'Détail fonctionnement'!$A$5:$A$505,"S1",'Détail fonctionnement'!$B$5:$B$505,"ODALYS CI",'Détail fonctionnement'!$C$5:$C$505,"FOURNISSEURS - FGX",'Détail fonctionnement'!$G$5:$G$505,"O") | Y10: =SUMIFS('Détail fonctionnement'!$J$5:$J$505,'Détail fonctionnement'!$A$5:$A$505,"S1",'Détail fonctionnement'!$B$5:$B$505,"AB CENTER",'Détail fonctionnement'!$C$5:$C$505,"FOURNISSEURS - FGX",'Détail fonctionnement'!$G$5:$G$505,"O") | AA10: =SUMIFS('Détail fonctionnement'!$J$5:$J$505,'Détail fonctionnement'!$A$5:$A$505,"S1",'Détail fonctionnement'!$B$5:$B$505,"RHD CI",'Détail fonctionnement'!$C$5:$C$505,"FOURNISSEURS - FGX",'Détail fonctionnement'!$G$5:$G$505,"O")
A11: IMPÔTS | C11: =SUMIFS('Détail fonctionnement'!$J$5:$J$505,'Détail fonctionnement'!$A$5:$A$505,"S1",'Détail fonctionnement'!$B$5:$B$505,"TERASSON",'Détail fonctionnement'!$C$5:$C$505,"IMPÔTS ET TAXES",'Détail fonctionnement'!$G$5:$G$505,"O") | E11: =SUMIFS('Détail fonctionnement'!$J$5:$J$505,'Détail fonctionnement'!$A$5:$A$505,"S1",'Détail fonctionnement'!$B$5:$B$505,"PICI",'Détail fonctionnement'!$C$5:$C$505,"IMPÔTS ET TAXES",'Détail fonctionnement'!$G$5:$G$505,"O") | H11: =SUMIFS('Détail fonctionnement'!$J$5:$J$505,'Détail fonctionnement'!$A$5:$A$505,"S1",'Détail fonctionnement'!$B$5:$B$505,"FIRST",'Détail fonctionnement'!$C$5:$C$505,"IMPÔTS ET TAXES",'Détail fonctionnement'!$G$5:$G$505,"O") | L11: =SUMIFS('Détail fonctionnement'!$J$5:$J$505,'Détail fonctionnement'!$A$5:$A$505,"S1",'Détail fonctionnement'!$B$5:$B$505,"RIVIERA",'Détail fonctionnement'!$C$5:$C$505,"IMPÔTS ET TAXES",'Détail fonctionnement'!$G$5:$G$505,"O") | N11: =SUMIFS('Détail fonctionnement'!$J$5:$J$505,'Détail fonctionnement'!$A$5:$A$505,"S1",'Détail fonctionnement'!$B$5:$B$505,"SCO AO",'Détail fonctionnement'!$C$5:$C$505,"IMPÔTS ET TAXES",'Détail fonctionnement'!$G$5:$G$505,"O") | R11: =SUMIFS('Détail fonctionnement'!$J$5:$J$505,'Détail fonctionnement'!$A$5:$A$505,"S1",'Détail fonctionnement'!$B$5:$B$505,"IMMONEUF",'Détail fonctionnement'!$C$5:$C$505,"IMPÔTS ET TAXES",'Détail fonctionnement'!$G$5:$G$505,"O") | U11: =SUMIFS('Détail fonctionnement'!$J$5:$J$505,'Détail fonctionnement'!$A$5:$A$505,"S1",'Détail fonctionnement'!$B$5:$B$505,"FINAFRICA",'Détail fonctionnement'!$C$5:$C$505,"IMPÔTS ET TAXES",'Détail fonctionnement'!$G$5:$G$505,"O") | W11: =SUMIFS('Détail fonctionnement'!$J$5:$J$505,'Détail fonctionnement'!$A$5:$A$505,"S1",'Détail fonctionnement'!$B$5:$B$505,"INFI SOFT",'Détail fonctionnement'!$C$5:$C$505,"IMPÔTS ET TAXES",'Détail fonctionnement'!$G$5:$G$505,"O") | X11: =SUMIFS('Détail fonctionnement'!$J$5:$J$505,'Détail fonctionnement'!$A$5:$A$505,"S1",'Détail fonctionnement'!$B$5:$B$505,"ODALYS CI",'Détail fonctionnement'!$C$5:$C$505,"IMPÔTS ET TAXES",'Détail fonctionnement'!$G$5:$G$505,"O") | Y11: =SUMIFS('Détail fonctionnement'!$J$5:$J$505,'Détail fonctionnement'!$A$5:$A$505,"S1",'Détail fonctionnement'!$B$5:$B$505,"AB CENTER",'Détail fonctionnement'!$C$5:$C$505,"IMPÔTS ET TAXES",'Détail fonctionnement'!$G$5:$G$505,"O") | AA11: =SUMIFS('Détail fonctionnement'!$J$5:$J$505,'Détail fonctionnement'!$A$5:$A$505,"S1",'Détail fonctionnement'!$B$5:$B$505,"RHD CI",'Détail fonctionnement'!$C$5:$C$505,"IMPÔTS ET TAXES",'Détail fonctionnement'!$G$5:$G$505,"O")
A12: CHARGES SOCIALES | C12: =SUMIFS('Détail fonctionnement'!$J$5:$J$505,'Détail fonctionnement'!$A$5:$A$505,"S1",'Détail fonctionnement'!$B$5:$B$505,"TERASSON",'Détail fonctionnement'!$C$5:$C$505,"CHARGES SOCIALES",'Détail fonctionnement'!$G$5:$G$505,"O") | E12: =SUMIFS('Détail fonctionnement'!$J$5:$J$505,'Détail fonctionnement'!$A$5:$A$505,"S1",'Détail fonctionnement'!$B$5:$B$505,"PICI",'Détail fonctionnement'!$C$5:$C$505,"CHARGES SOCIALES",'Détail fonctionnement'!$G$5:$G$505,"O") | H12: =SUMIFS('Détail fonctionnement'!$J$5:$J$505,'Détail fonctionnement'!$A$5:$A$505,"S1",'Détail fonctionnement'!$B$5:$B$505,"FIRST",'Détail fonctionnement'!$C$5:$C$505,"CHARGES SOCIALES",'Détail fonctionnement'!$G$5:$G$505,"O") | L12: =SUMIFS('Détail fonctionnement'!$J$5:$J$505,'Détail fonctionnement'!$A$5:$A$505,"S1",'Détail fonctionnement'!$B$5:$B$505,"RIVIERA",'Détail fonctionnement'!$C$5:$C$505,"CHARGES SOCIALES",'Détail fonctionnement'!$G$5:$G$505,"O") | N12: =SUMIFS('Détail fonctionnement'!$J$5:$J$505,'Détail fonctionnement'!$A$5:$A$505,"S1",'Détail fonctionnement'!$B$5:$B$505,"SCO AO",'Détail fonctionnement'!$C$5:$C$505,"CHARGES SOCIALES",'Détail fonctionnement'!$G$5:$G$505,"O") | R12: =SUMIFS('Détail fonctionnement'!$J$5:$J$505,'Détail fonctionnement'!$A$5:$A$505,"S1",'Détail fonctionnement'!$B$5:$B$505,"IMMONEUF",'Détail fonctionnement'!$C$5:$C$505,"CHARGES SOCIALES",'Détail fonctionnement'!$G$5:$G$505,"O") | U12: =SUMIFS('Détail fonctionnement'!$J$5:$J$505,'Détail fonctionnement'!$A$5:$A$505,"S1",'Détail fonctionnement'!$B$5:$B$505,"FINAFRICA",'Détail fonctionnement'!$C$5:$C$505,"CHARGES SOCIALES",'Détail fonctionnement'!$G$5:$G$505,"O") | W12: =SUMIFS('Détail fonctionnement'!$J$5:$J$505,'Détail fonctionnement'!$A$5:$A$505,"S1",'Détail fonctionnement'!$B$5:$B$505,"INFI SOFT",'Détail fonctionnement'!$C$5:$C$505,"CHARGES SOCIALES",'Détail fonctionnement'!$G$5:$G$505,"O") | X12: =SUMIFS('Détail fonctionnement'!$J$5:$J$505,'Détail fonctionnement'!$A$5:$A$505,"S1",'Détail fonctionnement'!$B$5:$B$505,"ODALYS CI",'Détail fonctionnement'!$C$5:$C$505,"CHARGES SOCIALES",'Détail fonctionnement'!$G$5:$G$505,"O") | Y12: =SUMIFS('Détail fonctionnement'!$J$5:$J$505,'Détail fonctionnement'!$A$5:$A$505,"S1",'Détail fonctionnement'!$B$5:$B$505,"AB CENTER",'Détail fonctionnement'!$C$5:$C$505,"CHARGES SOCIALES",'Détail fonctionnement'!$G$5:$G$505,"O") | AA12: =SUMIFS('Détail fonctionnement'!$J$5:$J$505,'Détail fonctionnement'!$A$5:$A$505,"S1",'Détail fonctionnement'!$B$5:$B$505,"RHD CI",'Détail fonctionnement'!$C$5:$C$505,"CHARGES SOCIALES",'Détail fonctionnement'!$G$5:$G$505,"O")
A13: SALAIRES | C13: =SUMIFS('Détail fonctionnement'!$J$5:$J$505,'Détail fonctionnement'!$A$5:$A$505,"S1",'Détail fonctionnement'!$B$5:$B$505,"TERASSON",'Détail fonctionnement'!$C$5:$C$505,"SALAIRES",'Détail fonctionnement'!$G$5:$G$505,"O") | E13: =SUMIFS('Détail fonctionnement'!$J$5:$J$505,'Détail fonctionnement'!$A$5:$A$505,"S1",'Détail fonctionnement'!$B$5:$B$505,"PICI",'Détail fonctionnement'!$C$5:$C$505,"SALAIRES",'Détail fonctionnement'!$G$5:$G$505,"O") | H13: =SUMIFS('Détail fonctionnement'!$J$5:$J$505,'Détail fonctionnement'!$A$5:$A$505,"S1",'Détail fonctionnement'!$B$5:$B$505,"FIRST",'Détail fonctionnement'!$C$5:$C$505,"SALAIRES",'Détail fonctionnement'!$G$5:$G$505,"O") | L13: =SUMIFS('Détail fonctionnement'!$J$5:$J$505,'Détail fonctionnement'!$A$5:$A$505,"S1",'Détail fonctionnement'!$B$5:$B$505,"RIVIERA",'Détail fonctionnement'!$C$5:$C$505,"SALAIRES",'Détail fonctionnement'!$G$5:$G$505,"O") | N13: =SUMIFS('Détail fonctionnement'!$J$5:$J$505,'Détail fonctionnement'!$A$5:$A$505,"S1",'Détail fonctionnement'!$B$5:$B$505,"SCO AO",'Détail fonctionnement'!$C$5:$C$505,"SALAIRES",'Détail fonctionnement'!$G$5:$G$505,"O") | R13: =SUMIFS('Détail fonctionnement'!$J$5:$J$505,'Détail fonctionnement'!$A$5:$A$505,"S1",'Détail fonctionnement'!$B$5:$B$505,"IMMONEUF",'Détail fonctionnement'!$C$5:$C$505,"SALAIRES",'Détail fonctionnement'!$G$5:$G$505,"O") | U13: =SUMIFS('Détail fonctionnement'!$J$5:$J$505,'Détail fonctionnement'!$A$5:$A$505,"S1",'Détail fonctionnement'!$B$5:$B$505,"FINAFRICA",'Détail fonctionnement'!$C$5:$C$505,"SALAIRES",'Détail fonctionnement'!$G$5:$G$505,"O") | W13: =SUMIFS('Détail fonctionnement'!$J$5:$J$505,'Détail fonctionnement'!$A$5:$A$505,"S1",'Détail fonctionnement'!$B$5:$B$505,"INFI SOFT",'Détail fonctionnement'!$C$5:$C$505,"SALAIRES",'Détail fonctionnement'!$G$5:$G$505,"O") | X13: =SUMIFS('Détail fonctionnement'!$J$5:$J$505,'Détail fonctionnement'!$A$5:$A$505,"S1",'Détail fonctionnement'!$B$5:$B$505,"ODALYS CI",'Détail fonctionnement'!$C$5:$C$505,"SALAIRES",'Détail fonctionnement'!$G$5:$G$505,"O") | Y13: =SUMIFS('Détail fonctionnement'!$J$5:$J$505,'Détail fonctionnement'!$A$5:$A$505,"S1",'Détail fonctionnement'!$B$5:$B$505,"AB CENTER",'Détail fonctionnement'!$C$5:$C$505,"SALAIRES",'Détail fonctionnement'!$G$5:$G$505,"O") | AA13: =SUMIFS('Détail fonctionnement'!$J$5:$J$505,'Détail fonctionnement'!$A$5:$A$505,"S1",'Détail fonctionnement'!$B$5:$B$505,"RHD CI",'Détail fonctionnement'!$C$5:$C$505,"SALAIRES",'Détail fonctionnement'!$G$5:$G$505,"O")
A14: ÉCHÉANCES | C14: =SUMIFS('Détail fonctionnement'!$J$5:$J$505,'Détail fonctionnement'!$A$5:$A$505,"S1",'Détail fonctionnement'!$B$5:$B$505,"TERASSON",'Détail fonctionnement'!$C$5:$C$505,"REMBOURSEMENT DE PRÊTS",'Détail fonctionnement'!$G$5:$G$505,"O") | E14: =SUMIFS('Détail fonctionnement'!$J$5:$J$505,'Détail fonctionnement'!$A$5:$A$505,"S1",'Détail fonctionnement'!$B$5:$B$505,"PICI",'Détail fonctionnement'!$C$5:$C$505,"REMBOURSEMENT DE PRÊTS",'Détail fonctionnement'!$G$5:$G$505,"O") | H14: =SUMIFS('Détail fonctionnement'!$J$5:$J$505,'Détail fonctionnement'!$A$5:$A$505,"S1",'Détail fonctionnement'!$B$5:$B$505,"FIRST",'Détail fonctionnement'!$C$5:$C$505,"REMBOURSEMENT DE PRÊTS",'Détail fonctionnement'!$G$5:$G$505,"O") | L14: =SUMIFS('Détail fonctionnement'!$J$5:$J$505,'Détail fonctionnement'!$A$5:$A$505,"S1",'Détail fonctionnement'!$B$5:$B$505,"RIVIERA",'Détail fonctionnement'!$C$5:$C$505,"REMBOURSEMENT DE PRÊTS",'Détail fonctionnement'!$G$5:$G$505,"O") | N14: =SUMIFS('Détail fonctionnement'!$J$5:$J$505,'Détail fonctionnement'!$A$5:$A$505,"S1",'Détail fonctionnement'!$B$5:$B$505,"SCO AO",'Détail fonctionnement'!$C$5:$C$505,"REMBOURSEMENT DE PRÊTS",'Détail fonctionnement'!$G$5:$G$505,"O") | R14: =SUMIFS('Détail fonctionnement'!$J$5:$J$505,'Détail fonctionnement'!$A$5:$A$505,"S1",'Détail fonctionnement'!$B$5:$B$505,"IMMONEUF",'Détail fonctionnement'!$C$5:$C$505,"REMBOURSEMENT DE PRÊTS",'Détail fonctionnement'!$G$5:$G$505,"O") | U14: =SUMIFS('Détail fonctionnement'!$J$5:$J$505,'Détail fonctionnement'!$A$5:$A$505,"S1",'Détail fonctionnement'!$B$5:$B$505,"FINAFRICA",'Détail fonctionnement'!$C$5:$C$505,"REMBOURSEMENT DE PRÊTS",'Détail fonctionnement'!$G$5:$G$505,"O") | W14: =SUMIFS('Détail fonctionnement'!$J$5:$J$505,'Détail fonctionnement'!$A$5:$A$505,"S1",'Détail fonctionnement'!$B$5:$B$505,"INFI SOFT",'Détail fonctionnement'!$C$5:$C$505,"REMBOURSEMENT DE PRÊTS",'Détail fonctionnement'!$G$5:$G$505,"O") | X14: =SUMIFS('Détail fonctionnement'!$J$5:$J$505,'Détail fonctionnement'!$A$5:$A$505,"S1",'Détail fonctionnement'!$B$5:$B$505,"ODALYS CI",'Détail fonctionnement'!$C$5:$C$505,"REMBOURSEMENT DE PRÊTS",'Détail fonctionnement'!$G$5:$G$505,"O") | Y14: =SUMIFS('Détail fonctionnement'!$J$5:$J$505,'Détail fonctionnement'!$A$5:$A$505,"S1",'Détail fonctionnement'!$B$5:$B$505,"AB CENTER",'Détail fonctionnement'!$C$5:$C$505,"REMBOURSEMENT DE PRÊTS",'Détail fonctionnement'!$G$5:$G$505,"O") | AA14: =SUMIFS('Détail fonctionnement'!$J$5:$J$505,'Détail fonctionnement'!$A$5:$A$505,"S1",'Détail fonctionnement'!$B$5:$B$505,"RHD CI",'Détail fonctionnement'!$C$5:$C$505,"REMBOURSEMENT DE PRÊTS",'Détail fonctionnement'!$G$5:$G$505,"O") | AB14: Échéances de prêts FIRST : dépenses de fonctionnement, compte payeur de FIRST
A15: AUTRES (ENCAISSEMENTS, DIVERS) | C15: =SUMIFS('Détail fonctionnement'!$J$5:$J$505,'Détail fonctionnement'!$A$5:$A$505,"S1",'Détail fonctionnement'!$B$5:$B$505,"TERASSON",'Détail fonctionnement'!$C$5:$C$505,"AUTRES DÉCAISSEMENTS",'Détail fonctionnement'!$G$5:$G$505,"O")+SUMIFS('Détail fonctionnement'!$J$5:$J$505,'Détail fonctionnement'!$A$5:$A$505,"S1",'Détail fonctionnement'!$B$5:$B$505,"TERASSON",'Détail fonctionnement'!$C$5:$C$505,"ENCAISSEMENTS",'Détail fonctionnement'!$G$5:$G$505,"O") | E15: =SUMIFS('Détail fonctionnement'!$J$5:$J$505,'Détail fonctionnement'!$A$5:$A$505,"S1",'Détail fonctionnement'!$B$5:$B$505,"PICI",'Détail fonctionnement'!$C$5:$C$505,"AUTRES DÉCAISSEMENTS",'Détail fonctionnement'!$G$5:$G$505,"O")+SUMIFS('Détail fonctionnement'!$J$5:$J$505,'Détail fonctionnement'!$A$5:$A$505,"S1",'Détail fonctionnement'!$B$5:$B$505,"PICI",'Détail fonctionnement'!$C$5:$C$505,"ENCAISSEMENTS",'Détail fonctionnement'!$G$5:$G$505,"O") | H15: =SUMIFS('Détail fonctionnement'!$J$5:$J$505,'Détail fonctionnement'!$A$5:$A$505,"S1",'Détail fonctionnement'!$B$5:$B$505,"FIRST",'Détail fonctionnement'!$C$5:$C$505,"AUTRES DÉCAISSEMENTS",'Détail fonctionnement'!$G$5:$G$505,"O")+SUMIFS('Détail fonctionnement'!$J$5:$J$505,'Détail fonctionnement'!$A$5:$A$505,"S1",'Détail fonctionnement'!$B$5:$B$505,"FIRST",'Détail fonctionnement'!$C$5:$C$505,"ENCAISSEMENTS",'Détail fonctionnement'!$G$5:$G$505,"O") | L15: =SUMIFS('Détail fonctionnement'!$J$5:$J$505,'Détail fonctionnement'!$A$5:$A$505,"S1",'Détail fonctionnement'!$B$5:$B$505,"RIVIERA",'Détail fonctionnement'!$C$5:$C$505,"AUTRES DÉCAISSEMENTS",'Détail fonctionnement'!$G$5:$G$505,"O")+SUMIFS('Détail fonctionnement'!$J$5:$J$505,'Détail fonctionnement'!$A$5:$A$505,"S1",'Détail fonctionnement'!$B$5:$B$505,"RIVIERA",'Détail fonctionnement'!$C$5:$C$505,"ENCAISSEMENTS",'Détail fonctionnement'!$G$5:$G$505,"O") | N15: =SUMIFS('Détail fonctionnement'!$J$5:$J$505,'Détail fonctionnement'!$A$5:$A$505,"S1",'Détail fonctionnement'!$B$5:$B$505,"SCO AO",'Détail fonctionnement'!$C$5:$C$505,"AUTRES DÉCAISSEMENTS",'Détail fonctionnement'!$G$5:$G$505,"O")+SUMIFS('Détail fonctionnement'!$J$5:$J$505,'Détail fonctionnement'!$A$5:$A$505,"S1",'Détail fonctionnement'!$B$5:$B$505,"SCO AO",'Détail fonctionnement'!$C$5:$C$505,"ENCAISSEMENTS",'Détail fonctionnement'!$G$5:$G$505,"O") | R15: =SUMIFS('Détail fonctionnement'!$J$5:$J$505,'Détail fonctionnement'!$A$5:$A$505,"S1",'Détail fonctionnement'!$B$5:$B$505,"IMMONEUF",'Détail fonctionnement'!$C$5:$C$505,"AUTRES DÉCAISSEMENTS",'Détail fonctionnement'!$G$5:$G$505,"O")+SUMIFS('Détail fonctionnement'!$J$5:$J$505,'Détail fonctionnement'!$A$5:$A$505,"S1",'Détail fonctionnement'!$B$5:$B$505,"IMMONEUF",'Détail fonctionnement'!$C$5:$C$505,"ENCAISSEMENTS",'Détail fonctionnement'!$G$5:$G$505,"O") | U15: =SUMIFS('Détail fonctionnement'!$J$5:$J$505,'Détail fonctionnement'!$A$5:$A$505,"S1",'Détail fonctionnement'!$B$5:$B$505,"FINAFRICA",'Détail fonctionnement'!$C$5:$C$505,"AUTRES DÉCAISSEMENTS",'Détail fonctionnement'!$G$5:$G$505,"O")+SUMIFS('Détail fonctionnement'!$J$5:$J$505,'Détail fonctionnement'!$A$5:$A$505,"S1",'Détail fonctionnement'!$B$5:$B$505,"FINAFRICA",'Détail fonctionnement'!$C$5:$C$505,"ENCAISSEMENTS",'Détail fonctionnement'!$G$5:$G$505,"O") | W15: =SUMIFS('Détail fonctionnement'!$J$5:$J$505,'Détail fonctionnement'!$A$5:$A$505,"S1",'Détail fonctionnement'!$B$5:$B$505,"INFI SOFT",'Détail fonctionnement'!$C$5:$C$505,"AUTRES DÉCAISSEMENTS",'Détail fonctionnement'!$G$5:$G$505,"O")+SUMIFS('Détail fonctionnement'!$J$5:$J$505,'Détail fonctionnement'!$A$5:$A$505,"S1",'Détail fonctionnement'!$B$5:$B$505,"INFI SOFT",'Détail fonctionnement'!$C$5:$C$505,"ENCAISSEMENTS",'Détail fonctionnement'!$G$5:$G$505,"O") | X15: =SUMIFS('Détail fonctionnement'!$J$5:$J$505,'Détail fonctionnement'!$A$5:$A$505,"S1",'Détail fonctionnement'!$B$5:$B$505,"ODALYS CI",'Détail fonctionnement'!$C$5:$C$505,"AUTRES DÉCAISSEMENTS",'Détail fonctionnement'!$G$5:$G$505,"O")+SUMIFS('Détail fonctionnement'!$J$5:$J$505,'Détail fonctionnement'!$A$5:$A$505,"S1",'Détail fonctionnement'!$B$5:$B$505,"ODALYS CI",'Détail fonctionnement'!$C$5:$C$505,"ENCAISSEMENTS",'Détail fonctionnement'!$G$5:$G$505,"O") | Y15: =SUMIFS('Détail fonctionnement'!$J$5:$J$505,'Détail fonctionnement'!$A$5:$A$505,"S1",'Détail fonctionnement'!$B$5:$B$505,"AB CENTER",'Détail fonctionnement'!$C$5:$C$505,"AUTRES DÉCAISSEMENTS",'Détail fonctionnement'!$G$5:$G$505,"O")+SUMIFS('Détail fonctionnement'!$J$5:$J$505,'Détail fonctionnement'!$A$5:$A$505,"S1",'Détail fonctionnement'!$B$5:$B$505,"AB CENTER",'Détail fonctionnement'!$C$5:$C$505,"ENCAISSEMENTS",'Détail fonctionnement'!$G$5:$G$505,"O") | AA15: =SUMIFS('Détail fonctionnement'!$J$5:$J$505,'Détail fonctionnement'!$A$5:$A$505,"S1",'Détail fonctionnement'!$B$5:$B$505,"RHD CI",'Détail fonctionnement'!$C$5:$C$505,"AUTRES DÉCAISSEMENTS",'Détail fonctionnement'!$G$5:$G$505,"O")+SUMIFS('Détail fonctionnement'!$J$5:$J$505,'Détail fonctionnement'!$A$5:$A$505,"S1",'Détail fonctionnement'!$B$5:$B$505,"RHD CI",'Détail fonctionnement'!$C$5:$C$505,"ENCAISSEMENTS",'Détail fonctionnement'!$G$5:$G$505,"O")
A16: ENREGISTREMENTS | C16: =SUMIFS('Détail fonctionnement'!$J$5:$J$505,'Détail fonctionnement'!$A$5:$A$505,"S1",'Détail fonctionnement'!$B$5:$B$505,"TERASSON",'Détail fonctionnement'!$C$5:$C$505,"ENREGISTREMENTS",'Détail fonctionnement'!$G$5:$G$505,"O") | E16: =SUMIFS('Détail fonctionnement'!$J$5:$J$505,'Détail fonctionnement'!$A$5:$A$505,"S1",'Détail fonctionnement'!$B$5:$B$505,"PICI",'Détail fonctionnement'!$C$5:$C$505,"ENREGISTREMENTS",'Détail fonctionnement'!$G$5:$G$505,"O") | H16: =SUMIFS('Détail fonctionnement'!$J$5:$J$505,'Détail fonctionnement'!$A$5:$A$505,"S1",'Détail fonctionnement'!$B$5:$B$505,"FIRST",'Détail fonctionnement'!$C$5:$C$505,"ENREGISTREMENTS",'Détail fonctionnement'!$G$5:$G$505,"O") | L16: =SUMIFS('Détail fonctionnement'!$J$5:$J$505,'Détail fonctionnement'!$A$5:$A$505,"S1",'Détail fonctionnement'!$B$5:$B$505,"RIVIERA",'Détail fonctionnement'!$C$5:$C$505,"ENREGISTREMENTS",'Détail fonctionnement'!$G$5:$G$505,"O") | N16: =SUMIFS('Détail fonctionnement'!$J$5:$J$505,'Détail fonctionnement'!$A$5:$A$505,"S1",'Détail fonctionnement'!$B$5:$B$505,"SCO AO",'Détail fonctionnement'!$C$5:$C$505,"ENREGISTREMENTS",'Détail fonctionnement'!$G$5:$G$505,"O") | R16: =SUMIFS('Détail fonctionnement'!$J$5:$J$505,'Détail fonctionnement'!$A$5:$A$505,"S1",'Détail fonctionnement'!$B$5:$B$505,"IMMONEUF",'Détail fonctionnement'!$C$5:$C$505,"ENREGISTREMENTS",'Détail fonctionnement'!$G$5:$G$505,"O") | U16: =SUMIFS('Détail fonctionnement'!$J$5:$J$505,'Détail fonctionnement'!$A$5:$A$505,"S1",'Détail fonctionnement'!$B$5:$B$505,"FINAFRICA",'Détail fonctionnement'!$C$5:$C$505,"ENREGISTREMENTS",'Détail fonctionnement'!$G$5:$G$505,"O") | W16: =SUMIFS('Détail fonctionnement'!$J$5:$J$505,'Détail fonctionnement'!$A$5:$A$505,"S1",'Détail fonctionnement'!$B$5:$B$505,"INFI SOFT",'Détail fonctionnement'!$C$5:$C$505,"ENREGISTREMENTS",'Détail fonctionnement'!$G$5:$G$505,"O") | X16: =SUMIFS('Détail fonctionnement'!$J$5:$J$505,'Détail fonctionnement'!$A$5:$A$505,"S1",'Détail fonctionnement'!$B$5:$B$505,"ODALYS CI",'Détail fonctionnement'!$C$5:$C$505,"ENREGISTREMENTS",'Détail fonctionnement'!$G$5:$G$505,"O") | Y16: =SUMIFS('Détail fonctionnement'!$J$5:$J$505,'Détail fonctionnement'!$A$5:$A$505,"S1",'Détail fonctionnement'!$B$5:$B$505,"AB CENTER",'Détail fonctionnement'!$C$5:$C$505,"ENREGISTREMENTS",'Détail fonctionnement'!$G$5:$G$505,"O") | AA16: =SUMIFS('Détail fonctionnement'!$J$5:$J$505,'Détail fonctionnement'!$A$5:$A$505,"S1",'Détail fonctionnement'!$B$5:$B$505,"RHD CI",'Détail fonctionnement'!$C$5:$C$505,"ENREGISTREMENTS",'Détail fonctionnement'!$G$5:$G$505,"O") | AB16: Hors besoin (droits d'enregistrement, Retenu = N)
A17: Total | B17: =SUM(B7:B16) | C17: =SUM(C7:C16) | D17: =SUM(D7:D16) | E17: =SUM(E7:E16) | F17: =SUM(F7:F16) | G17: =SUM(G7:G16) | H17: =SUM(H7:H16) | I17: =SUM(I7:I16) | ... AA17: =SUM(AA7:AA16)
A18: Solde au 30/09/2026 | B18: ='Position CI 30-09'!F29 | C18: ='Position CI 30-09'!F10 | D18: ='Position CI 30-09'!F11 | E18: ='Position CI 30-09'!F6 | F18: ='Position CI 30-09'!F5 | G18: ='Position CI 30-09'!F7 | H18: ='Position CI 30-09'!F9 | I18: ='Position CI 30-09'!F8 | J18: ='Position CI 30-09'!F28 | K18: ='Position CI 30-09'!F13 | L18: ='Position CI 30-09'!F12 | M18: ='Position CI 30-09'!F16 | N18: ='Position CI 30-09'!F15 | O18: ='Position CI 30-09'!F14 | P18: ='Position CI 30-09'!F17 | Q18: ='Position CI 30-09'!F18 | R18: ='Position CI 30-09'!F23 | S18: ='Position CI 30-09'!F25 | T18: ='Position CI 30-09'!F24 | U18: ='Position CI 30-09'!F19 | V18: ='Position CI 30-09'!F20 | W18: ='Position CI 30-09'!F26 | X18: ='Position CI 30-09'!F27 | Y18: ='Position CI 30-09'!F22 | Z18: ='Position CI 30-09'!F21 | AA18: 0
A19: Solde théorique fin S1 (11/10/2026) | B19: =B17+B18 | C19: =C17+C18 | D19: =D17+D18 | E19: =E17+E18 | F19: =F17+F18 | G19: =G17+G18 | H19: =H17+H18 | I19: =I17+I18 | ... AA19: =AA17+AA18
A20: Reste à financer (spot) ou à reporter | B20: =IF(B19<0,-B19,0) | C20: =IF(C19<0,-C19,0) | D20: =IF(D19<0,-D19,0) | E20: =IF(E19<0,-E19,0) | F20: =IF(F19<0,-F19,0) | G20: =IF(G19<0,-G19,0) | H20: =IF(H19<0,-H19,0) | I20: =IF(I19<0,-I19,0) | ... AA20: =IF(AA19<0,-AA19,0) | AB20: =SUM(B20:AA20)
A23: Virements à passer (modifiables : les nivellements et les soldes ci-dessus se recalculent)
A24: Type de nivellement | B24: N° | C24: Compte source | E24: Compte bénéficiaire | H24: Montant FCFA | I24: Motif
A25: AUTRES NIVELLEMENTS | B25: 1 | C25: RIVIERA PARK – BNI courant | E25: RIVIERA PARK – SG | H25: 500000000
E56: Total des virements | H56: =SUM(H25:H55)
A57: Comptes (liste de saisie)
A58: TERASSON – BNI fonds projet
A59: TERASSON – SG
A60: TERASSON – ECO
A61: PICI – STB
A62: PICI – SG
A63: PICI – ECO
A64: SCI FIRST – STB
A65: SCI FIRST – SG
A66: RIVIERA PARK – BNI fonds projet
A67: RIVIERA PARK – BNI courant
A68: RIVIERA PARK – SG
... A83: RHD CI – payé par PICI

Sheet Détail fonctionnement
A1: Détail des flux de fonctionnement (frais de structure) – FCFA
A2: Paiement effectué : saisir le montant payé en H (et sa date en I) ; seul le reste à payer (J) alimente le reporting. Paiement non prévu : ajouter une ligne en bas (semaine, entité, nature, libellé, montant négatif, Retenu = O).
A4: Semaine | B4: Entité | C4: Nature | D4: Fournisseur / libellé | E4: Montant FCFA | F4: Montant € | G4: Retenu (O/N) | H4: Payé FCFA (saisie) | I4: Date de paiement | J4: Reste à payer FCFA
A5: S1 | B5: PICI | C5: FOURNISSEURS - FGX | D5: BURMA | E5: -628015 | F5: =E5/'Reporting Hebdo'!$E$3 | G5: O | J5: =IF(E5<0,MIN(0,E5+N(H5)),MAX(0,E5-N(H5)))
A6: S1 | B6: PICI | C6: FOURNISSEURS - FGX | D6: CABINET JEAN-LUC RUELLE | E6: -5947200 | F6: =E6/'Reporting Hebdo'!$E$3 | G6: O | J6: =IF(E6<0,MIN(0,E6+N(H6)),MAX(0,E6-N(H6)))
A7: S1 | B7: PICI | C7: FOURNISSEURS - FGX | D7: CIE | E7: -50 | F7: =E7/'Reporting Hebdo'!$E$3 | G7: O | J7: =IF(E7<0,MIN(0,E7+N(H7)),MAX(0,E7-N(H7)))
A8: S1 | B8: PICI | C8: FOURNISSEURS - FGX | D8: DHL | E8: -157910 | F8: =E8/'Reporting Hebdo'!$E$3 | G8: O | J8: =IF(E8<0,MIN(0,E8+N(H8)),MAX(0,E8-N(H8)))
A9: S1 | B9: PICI | C9: FOURNISSEURS - FGX | D9: FOURNISSEURS DIVERS | E9: -7734197 | F9: =E9/'Reporting Hebdo'!$E$3 | G9: O | J9: =IF(E9<0,MIN(0,E9+N(H9)),MAX(0,E9-N(H9)))
A10: S1 | B10: PICI | C10: FOURNISSEURS - FGX | D10: HORUS TRAD SARL | E10: -324500 | F10: =E10/'Reporting Hebdo'!$E$3 | G10: O | J10: =IF(E10<0,MIN(0,E10+N(H10)),MAX(0,E10-N(H10)))
A11: S1 | B11: PICI | C11: FOURNISSEURS - FGX | D11: HORUS TRAD SARL | E11: -324500 | F11: =E11/'Reporting Hebdo'!$E$3 | G11: O | J11: =IF(E11<0,MIN(0,E11+N(H11)),MAX(0,E11-N(H11)))
A12: S1 | B12: PICI | C12: FOURNISSEURS - FGX | D12: IMPACT | E12: -5443898 | F12: =E12/'Reporting Hebdo'!$E$3 | G12: O | J12: =IF(E12<0,MIN(0,E12+N(H12)),MAX(0,E12-N(H12)))
A13: S1 | B13: PICI | C13: FOURNISSEURS - FGX | D13: JULIE BASSONVILLE | E13: -342735 | F13: =E13/'Reporting Hebdo'!$E$3 | G13: O | J13: =IF(E13<0,MIN(0,E13+N(H13)),MAX(0,E13-N(H13)))
A14: S1 | B14: PICI | C14: FOURNISSEURS - FGX | D14: LAVIVA | E14: -34002 | F14: =E14/'Reporting Hebdo'!$E$3 | G14: O | J14: =IF(E14<0,MIN(0,E14+N(H14)),MAX(0,E14-N(H14)))
A15: S1 | B15: PICI | C15: FOURNISSEURS - FGX | D15: LAVIVA | E15: -44002 | F15: =E15/'Reporting Hebdo'!$E$3 | G15: O | J15: =IF(E15<0,MIN(0,E15+N(H15)),MAX(0,E15-N(H15)))
A16: S1 | B16: PICI | C16: FOURNISSEURS - FGX | D16: LOXEA | E16: -7954048 | F16: =E16/'Reporting Hebdo'!$E$3 | G16: O | J16: =IF(E16<0,MIN(0,E16+N(H16)),MAX(0,E16-N(H16)))
... A204: S2 | B204: FIRST | C204: ENCAISSEMENTS | D204: Loyer octobre 2026 – SIEMENS ENERGY SARL | E204: 6113285 | F204: =E204/'Reporting Hebdo'!$E$3 | G204: N | J204: =IF(E204<0,MIN(0,E204+N(H204)),MAX(0,E204-N(H204)))
J205: =IF(E205<0,MIN(0,E205+N(H205)),MAX(0,E205-N(H205)))
J206: =IF(E206<0,MIN(0,E206+N(H206)),MAX(0,E206-N(H206)))
J207: =IF(E207<0,MIN(0,E207+N(H207)),MAX(0,E207-N(H207)))
J208: =IF(E208<0,MIN(0,E208+N(H208)),MAX(0,E208-N(H208)))
J209: =IF(E209<0,MIN(0,E209+N(H209)),MAX(0,E209-N(H209)))
J210: =IF(E210<0,MIN(0,E210+N(H210)),MAX(0,E210-N(H210)))
J211: =IF(E211<0,MIN(0,E211+N(H211)),MAX(0,E211-N(H211)))
J212: =IF(E212<0,MIN(0,E212+N(H212)),MAX(0,E212-N(H212)))
J213: =IF(E213<0,MIN(0,E213+N(H213)),MAX(0,E213-N(H213)))
J214: =IF(E214<0,MIN(0,E214+N(H214)),MAX(0,E214-N(H214)))
J215: =IF(E215<0,MIN(0,E215+N(H215)),MAX(0,E215-N(H215)))
J216: =IF(E216<0,MIN(0,E216+N(H216)),MAX(0,E216-N(H216)))
... J505: =IF(E505<0,MIN(0,E505+N(H505)),MAX(0,E505-N(H505)))

Sheet Détail projets & dettes
A1: Détail des flux projets & dettes (comptes dédiés)
A2: Paiement effectué : saisir le montant payé en FCFA en K (et sa date en L) ; seul le reste à payer (M) alimente le reporting.
A4: Semaine | B4: Compte dédié (clé) | C4: Entité | D4: Nature | E4: Code | F4: Libellé | G4: Entreprise | H4: Montant € HT | I4: Montant FCFA | J4: Retenu (O/N) | K4: Payé FCFA (saisie) | L4: Date de paiement | M4: Reste à payer FCFA
A5: S1 | B5: TERASSON-PROJET | C5: TERASSON | D5: Foncier | E5: FON 0009 | F5: Géomètre | G5: KOUAMELAN | H5: -5802 | I5: =H5*'Reporting Hebdo'!$E$3 | J5: O | M5: =IF(I5<0,MIN(0,I5+N(K5)),MAX(0,I5-N(K5)))
A6: S1 | B6: TERASSON-PROJET | C6: TERASSON | D6: Travaux | F6: 09 BGTB | H6: -86158.96 | I6: =H6*'Reporting Hebdo'!$E$3 | J6: O | M6: =IF(I6<0,MIN(0,I6+N(K6)),MAX(0,I6-N(K6)))
A7: S1 | B7: TERASSON-PROJET | C7: TERASSON | D7: Travaux | E7: BCC 0009 | F7: Autres travaux | H7: -12500 | I7: =H7*'Reporting Hebdo'!$E$3 | J7: O | M7: =IF(I7<0,MIN(0,I7+N(K7)),MAX(0,I7-N(K7)))
A8: S1 | B8: TERASSON-PROJET | C8: TERASSON | D8: Travaux | E8: BCC 0017 | F8: 02 GROS ŒUVRE & INSTALLATION DE CHANTIER | H8: -598630.99 | I8: =H8*'Reporting Hebdo'!$E$3 | J8: O | K8: 392676186 | L8: 07/10/2026 | M8: =IF(I8<0,MIN(0,I8+N(K8)),MAX(0,I8-N(K8)))
A9: S1 | B9: TERASSON-PROJET | C9: TERASSON | D9: Travaux | E9: BCC 0023 | F9: 07 SERRURERIE | H9: -164209.05 | I9: =H9*'Reporting Hebdo'!$E$3 | J9: O | M9: =IF(I9<0,MIN(0,I9+N(K9)),MAX(0,I9-N(K9)))
A10: S1 | B10: TERASSON-PROJET | C10: TERASSON | D10: Travaux | E10: BCC 0024 | F10: 08 CFO | H10: -224940.6 | I10: =H10*'Reporting Hebdo'!$E$3 | J10: O | M10: =IF(I10<0,MIN(0,I10+N(K10)),MAX(0,I10-N(K10)))
A11: S1 | B11: TERASSON-PROJET | C11: TERASSON | D11: Travaux | E11: BCC 0025 | F11: 09A CFA /SSI /GTB | H11: -338435.85 | I11: =H11*'Reporting Hebdo'!$E$3 | J11: O | M11: =IF(I11<0,MIN(0,I11+N(K11)),MAX(0,I11-N(K11)))
A12: S1 | B12: TERASSON-PROJET | C12: TERASSON | D12: Honoraires | E12: HON 0001 | F12: Architecte | G12: ARCHICONCEPT / MAP | H12: -54903 | I12: =H12*'Reporting Hebdo'!$E$3 | J12: O | M12: =IF(I12<0,MIN(0,I12+N(K12)),MAX(0,I12-N(K12)))
A13: S1 | B13: TERASSON-PROJET | C13: TERASSON | D13: Honoraires | E13: HON 0001 | F13: Architecte | G13: ARCHICONCEPT / MAP | H13: -6577 | I13: =H13*'Reporting Hebdo'!$E$3 | J13: O | M13: =IF(I13<0,MIN(0,I13+N(K13)),MAX(0,I13-N(K13)))
A14: S1 | B14: TERASSON-PROJET | C14: TERASSON | D14: Honoraires | E14: HON 0002 | F14: BET / MOE / SSI | G14: SCO | H14: -82323.18 | I14: =H14*'Reporting Hebdo'!$E$3 | J14: O | K14: 2709103 | L14: 07/10/2026 | M14: =IF(I14<0,MIN(0,I14+N(K14)),MAX(0,I14-N(K14)))
A15: S1 | B15: TERASSON-PROJET | C15: TERASSON | D15: Honoraires | E15: HON 0005 | F15: Bureau de contrôle | G15: BUREAU VERITAS | H15: -8415.19 | I15: =H15*'Reporting Hebdo'!$E$3 | J15: O | M15: =IF(I15<0,MIN(0,I15+N(K15)),MAX(0,I15-N(K15)))
A16: S1 | B16: TERASSON-PROJET | C16: TERASSON | D16: Honoraires | E16: HON 0006 | F16: CSPS | G16: SOCOTEC | H16: -6738.37 | I16: =H16*'Reporting Hebdo'!$E$3 | J16: O | M16: =IF(I16<0,MIN(0,I16+N(K16)),MAX(0,I16-N(K16)))
A17: S1 | B17: TERASSON-PROJET | C17: TERASSON | D17: Honoraires | E17: HON 0007 | F17: E&S | G17: ANDE / ENVAL / INSUCO / BIOTOPE / IVOIRE HYDROGENE | H17: -105395.81 | I17: =H17*'Reporting Hebdo'!$E$3 | J17: O | M17: =IF(I17<0,MIN(0,I17+N(K17)),MAX(0,I17-N(K17)))
A18: S1 | B18: TERASSON-PROJET | C18: TERASSON | D18: Honoraires | E18: HON 0009 | F18: Divers honoraires | G18: PROJEX / DIPHONE / LUSEO / BET GAURY | H18: -7000 | I18: =H18*'Reporting Hebdo'!$E$3 | J18: O | M18: =IF(I18<0,MIN(0,I18+N(K18)),MAX(0,I18-N(K18)))
A19: S1 | B19: TERASSON-PROJET | C19: TERASSON | D19: Honoraires | E19: HON 0010 | F19: Retenue à la source (prestataires étrangers) | H19: -48527.84 | I19: =H19*'Reporting Hebdo'!$E$3 | J19: O | M19: =IF(I19<0,MIN(0,I19+N(K19)),MAX(0,I19-N(K19)))
A20: S1 | B20: TERASSON-PROJET | C20: TERASSON | D20: Autres dépenses | E20: AUD 0007 | F20: Frais Divers | G20: YABA & KUMBA / SINTALI / VOLTERE | H20: -10000 | I20: =H20*'Reporting Hebdo'!$E$3 | J20: O | M20: =IF(I20<0,MIN(0,I20+N(K20)),MAX(0,I20-N(K20)))
A21: S1 | B21: TERASSON-PROJET | C21: TERASSON | D21: Autres dépenses | E21: AUD 0012 | F21: Autres frais financiers (Frais de Due Diligence) | G21: DWF/IFC | H21: -1255555.2 | I21: =H21*'Reporting Hebdo'!$E$3 | J21: O | M21: =IF(I21<0,MIN(0,I21+N(K21)),MAX(0,I21-N(K21)))
A22: S1 | B22: TERASSON-PROJET | C22: TERASSON | D22: Frais financiers | E22: FFI 0001 | F22: Intérêts sur compte courant | H22: -128661.33 | I22: =H22*'Reporting Hebdo'!$E$3 | J22: O | M22: =IF(I22<0,MIN(0,I22+N(K22)),MAX(0,I22-N(K22)))
A23: S1 | B23: TERASSON-PROJET | C23: TERASSON | D23: Frais financiers | E23: FFI 0005 | F23: Frais Financiers Coupons Invest | H23: -212269.89 | I23: =H23*'Reporting Hebdo'!$E$3 | J23: O | M23: =IF(I23<0,MIN(0,I23+N(K23)),MAX(0,I23-N(K23)))
A24: S1 | B24: RIVIERA-PROJET | C24: RIVIERA | D24: Foncier | E24: FON 0009 | F24: Géomètre | G24: ATELIER TOPOGRAPHIQUE KOTOKOU / CYGE / SG2T | H24: -2000 | I24: =H24*'Reporting Hebdo'!$E$3 | J24: O | M24: =IF(I24<0,MIN(0,I24+N(K24)),MAX(0,I24-N(K24)))
A25: S1 | B25: RIVIERA-PROJET | C25: RIVIERA | D25: Foncier | E25: FON 0014 | F25: Sécurisation du site | G25: AIGLE ROYAL / RASCOM / SEG / ECS | H25: -6532.01 | I25: =H25*'Reporting Hebdo'!$E$3 | J25: O | M25: =IF(I25<0,MIN(0,I25+N(K25)),MAX(0,I25-N(K25)))
A26: S1 | B26: RIVIERA-PROJET | C26: RIVIERA | D26: Foncier | E26: FON 0018 | F26: Brche. Eau | G26: SODECI | H26: -9643.65 | I26: =H26*'Reporting Hebdo'!$E$3 | J26: O | M26: =IF(I26<0,MIN(0,I26+N(K26)),MAX(0,I26-N(K26)))
A27: S1 | B27: RIVIERA-PROJET | C27: RIVIERA | D27: Travaux | E27: BCC 0001 | F27: Démolitions | H27: -35324 | I27: =H27*'Reporting Hebdo'!$E$3 | J27: O | M27: =IF(I27<0,MIN(0,I27+N(K27)),MAX(0,I27-N(K27)))
A28: S1 | B28: RIVIERA-PROJET | C28: RIVIERA | D28: Travaux | E28: BCC 0002 | F28: Fondations spéciales | H28: -153276 | I28: =H28*'Reporting Hebdo'!$E$3 | J28: O | M28: =IF(I28<0,MIN(0,I28+N(K28)),MAX(0,I28-N(K28)))
A29: S1 | B29: RIVIERA-PROJET | C29: RIVIERA | D29: Travaux | E29: BCC 0013 | F29: 1B-VRD - Espaces verts | G29: UNISERV | H29: -318222.84 | I29: =H29*'Reporting Hebdo'!$E$3 | J29: O | M29: =IF(I29<0,MIN(0,I29+N(K29)),MAX(0,I29-N(K29)))
A30: S1 | B30: RIVIERA-PROJET | C30: RIVIERA | D30: Travaux | E30: BCC 0014 | F30: 2-Gros oeuvre | H30: -1078767.2 | I30: =H30*'Reporting Hebdo'!$E$3 | J30: O | M30: =IF(I30<0,MIN(0,I30+N(K30)),MAX(0,I30-N(K30)))
A31: S1 | B31: RIVIERA-PROJET | C31: RIVIERA | D31: Travaux | E31: BCC 0015 | F31: 3-Etancheite | H31: -114194.59 | I31: =H31*'Reporting Hebdo'!$E$3 | J31: O | M31: =IF(I31<0,MIN(0,I31+N(K31)),MAX(0,I31-N(K31)))
A32: S1 | B32: RIVIERA-PROJET | C32: RIVIERA | D32: Travaux | E32: BCC 0016 | F32: 4A-Charpente metallique | H32: -420171.15 | I32: =H32*'Reporting Hebdo'!$E$3 | J32: O | M32: =IF(I32<0,MIN(0,I32+N(K32)),MAX(0,I32-N(K32)))
A33: S1 | B33: RIVIERA-PROJET | C33: RIVIERA | D33: Travaux | E33: BCC 0017 | F33: 4B-Couverture & Bardage | H33: -215577.47 | I33: =H33*'Reporting Hebdo'!$E$3 | J33: O | M33: =IF(I33<0,MIN(0,I33+N(K33)),MAX(0,I33-N(K33)))
A34: S1 | B34: RIVIERA-PROJET | C34: RIVIERA | D34: Travaux | E34: BCC 0018 | F34: 5-Menuiseries exterieures | H34: -74507.76 | I34: =H34*'Reporting Hebdo'!$E$3 | J34: O | M34: =IF(I34<0,MIN(0,I34+N(K34)),MAX(0,I34-N(K34)))
A35: S1 | B35: RIVIERA-PROJET | C35: RIVIERA | D35: Travaux | E35: BCC 0020 | F35: 7-Serrurerie | H35: -92662.98 | I35: =H35*'Reporting Hebdo'!$E$3 | J35: O | M35: =IF(I35<0,MIN(0,I35+N(K35)),MAX(0,I35-N(K35)))
A36: S1 | B36: RIVIERA-PROJET | C36: RIVIERA | D36: Honoraires | E36: HON 0001 | F36: Architecte | G36: ZUO / CIA / MAP | H36: -59066.62 | I36: =H36*'Reporting Hebdo'!$E$3 | J36: O | M36: =IF(I36<0,MIN(0,I36+N(K36)),MAX(0,I36-N(K36)))
A37: S1 | B37: RIVIERA-PROJET | C37: RIVIERA | D37: Honoraires | E37: HON 0001 | F37: Architecte | G37: ZUO / CIA / MAP | H37: -18066.62 | I37: =H37*'Reporting Hebdo'!$E$3 | J37: O | M37: =IF(I37<0,MIN(0,I37+N(K37)),MAX(0,I37-N(K37)))
A38: S1 | B38: RIVIERA-PROJET | C38: RIVIERA | D38: Honoraires | E38: HON 0002 | F38: BET / MOE / SSI | G38: SCO | H38: -41399.65 | I38: =H38*'Reporting Hebdo'!$E$3 | J38: O | M38: =IF(I38<0,MIN(0,I38+N(K38)),MAX(0,I38-N(K38)))
A39: S1 | B39: RIVIERA-PROJET | C39: RIVIERA | D39: Honoraires | E39: HON 0005 | F39: Bureau de contrôle | G39: SOCOTEC | H39: -10236.62 | I39: =H39*'Reporting Hebdo'!$E$3 | J39: O | M39: =IF(I39<0,MIN(0,I39+N(K39)),MAX(0,I39-N(K39)))
A40: S1 | B40: RIVIERA-PROJET | C40: RIVIERA | D40: Honoraires | E40: HON 0006 | F40: CSPS | G40: SOCOTEC | H40: -4428 | I40: =H40*'Reporting Hebdo'!$E$3 | J40: O | M40: =IF(I40<0,MIN(0,I40+N(K40)),MAX(0,I40-N(K40)))
A41: S1 | B41: RIVIERA-PROJET | C41: RIVIERA | D41: Honoraires | E41: HON 0007 | F41: E&S | G41: INSUCO / BRL INGENIERIE/ANDE | H41: -13438.33 | I41: =H41*'Reporting Hebdo'!$E$3 | J41: O | M41: =IF(I41<0,MIN(0,I41+N(K41)),MAX(0,I41-N(K41)))
A42: S1 | B42: RIVIERA-PROJET | C42: RIVIERA | D42: Honoraires | E42: HON 0008 | F42: Diagnostic divers | H42: -9818 | I42: =H42*'Reporting Hebdo'!$E$3 | J42: O | M42: =IF(I42<0,MIN(0,I42+N(K42)),MAX(0,I42-N(K42)))
A43: S1 | B43: RIVIERA-PROJET | C43: RIVIERA | D43: Honoraires | E43: HON 0009 | F43: Divers honoraires | G43: AUXO / PROJEX / GSPM / HORECAF / HILLEL | H43: -8000 | I43: =H43*'Reporting Hebdo'!$E$3 | J43: O | M43: =IF(I43<0,MIN(0,I43+N(K43)),MAX(0,I43-N(K43)))
A44: S1 | B44: RIVIERA-PROJET | C44: RIVIERA | D44: Honoraires | E44: HON 0010 | F44: Retenue à la source (prestataires étrangers) | H44: -53450.46 | I44: =H44*'Reporting Hebdo'!$E$3 | J44: O | M44: =IF(I44<0,MIN(0,I44+N(K44)),MAX(0,I44-N(K44)))
A45: S1 | B45: RIVIERA-PROJET | C45: RIVIERA | D45: Autres dépenses | E45: AUD 0008 | F45: Publicité | G45: SHERPA/LES ATELIERS COOK IMPRIM | H45: -7000 | I45: =H45*'Reporting Hebdo'!$E$3 | J45: O | M45: =IF(I45<0,MIN(0,I45+N(K45)),MAX(0,I45-N(K45)))
A46: S1 | B46: RIVIERA-PROJET | C46: RIVIERA | D46: Frais financiers | E46: FFI 0001 | F46: Intérêts sur compte courant | H46: -214443.77 | I46: =H46*'Reporting Hebdo'!$E$3 | J46: O | M46: =IF(I46<0,MIN(0,I46+N(K46)),MAX(0,I46-N(K46)))
A47: S1 | B47: RIVIERA-PROJET | C47: RIVIERA | D47: Frais financiers | E47: FFI 0002 | F47: Produits financiers | H47: 75303.63 | I47: =H47*'Reporting Hebdo'!$E$3 | J47: O | M47: =IF(I47<0,MIN(0,I47+N(K47)),MAX(0,I47-N(K47)))
A48: S1 | B48: RIVIERA-PROJET | C48: RIVIERA | D48: Frais financiers | E48: FFI 0005 | F48: Frais Financiers Coupons Invest | H48: -146427.09 | I48: =H48*'Reporting Hebdo'!$E$3 | J48: O | M48: =IF(I48<0,MIN(0,I48+N(K48)),MAX(0,I48-N(K48)))
A49: S2 | B49: TERASSON-PROJET | C49: TERASSON | D49: Travaux | E49: BCC 0009 | F49: Autres travaux | H49: -12500 | I49: =H49*'Reporting Hebdo'!$E$3 | J49: O | M49: =IF(I49<0,MIN(0,I49+N(K49)),MAX(0,I49-N(K49)))
A50: S2 | B50: TERASSON-PROJET | C50: TERASSON | D50: Travaux | E50: BCC 0017 | F50: 02 GROS ŒUVRE & INSTALLATION DE CHANTIER | H50: -579003.74 | I50: =H50*'Reporting Hebdo'!$E$3 | J50: O | K50: 309280271 | L50: 07/10/2026 | M50: =IF(I50<0,MIN(0,I50+N(K50)),MAX(0,I50-N(K50)))
A51: S2 | B51: TERASSON-PROJET | C51: TERASSON | D51: Travaux | E51: BCC 0018 | F51: 03 ETANCHEITE | H51: -42223.48 | I51: =H51*'Reporting Hebdo'!$E$3 | J51: O | M51: =IF(I51<0,MIN(0,I51+N(K51)),MAX(0,I51-N(K51)))
A52: S2 | B52: TERASSON-PROJET | C52: TERASSON | D52: Travaux | E52: BCC 0034 | F52: CC ROOFTOP SURELEVATION BAT B | H52: -58400 | I52: =H52*'Reporting Hebdo'!$E$3 | J52: O | M52: =IF(I52<0,MIN(0,I52+N(K52)),MAX(0,I52-N(K52)))
A53: S2 | B53: TERASSON-PROJET | C53: TERASSON | D53: Honoraires | E53: HON 0007 | F53: E&S | G53: ANDE / ENVAL / INSUCO / BIOTOPE / IVOIRE HYDROGENE | H53: -4827.48 | I53: =H53*'Reporting Hebdo'!$E$3 | J53: O | M53: =IF(I53<0,MIN(0,I53+N(K53)),MAX(0,I53-N(K53)))
A54: S2 | B54: TERASSON-PROJET | C54: TERASSON | D54: Honoraires | E54: HON 0009 | F54: Divers honoraires | G54: PROJEX / DIPHONE / LUSEO / BET GAURY | H54: -8253 | I54: =H54*'Reporting Hebdo'!$E$3 | J54: O | M54: =IF(I54<0,MIN(0,I54+N(K54)),MAX(0,I54-N(K54)))
A55: S2 | B55: TERASSON-PROJET | C55: TERASSON | D55: Honoraires | E55: HON 0010 | F55: Retenue à la source (prestataires étrangers) | H55: -4731 | I55: =H55*'Reporting Hebdo'!$E$3 | J55: O | M55: =IF(I55<0,MIN(0,I55+N(K55)),MAX(0,I55-N(K55)))
A56: S2 | B56: TERASSON-PROJET | C56: TERASSON | D56: Autres dépenses | E56: AUD 0008 | F56: Publicité | G56: SHERPA | H56: -10000 | I56: =H56*'Reporting Hebdo'!$E$3 | J56: O | M56: =IF(I56<0,MIN(0,I56+N(K56)),MAX(0,I56-N(K56)))
A57: S2 | B57: RIVIERA-PROJET | C57: RIVIERA | D57: Foncier | E57: FON 0017 | F57: Brche. Electricité | G57: CI ENERGIES | H57: -22400 | I57: =H57*'Reporting Hebdo'!$E$3 | J57: O | M57: =IF(I57<0,MIN(0,I57+N(K57)),MAX(0,I57-N(K57)))
A58: S2 | B58: RIVIERA-PROJET | C58: RIVIERA | D58: Travaux | E58: BCC 0013 | F58: 1B-VRD - Espaces verts | G58: UNISERV | H58: -64093.98 | I58: =H58*'Reporting Hebdo'!$E$3 | J58: O | M58: =IF(I58<0,MIN(0,I58+N(K58)),MAX(0,I58-N(K58)))
A59: S2 | B59: RIVIERA-PROJET | C59: RIVIERA | D59: Travaux | E59: BCC 0014 | F59: 2-Gros oeuvre | H59: -495269.11 | I59: =H59*'Reporting Hebdo'!$E$3 | J59: O | M59: =IF(I59<0,MIN(0,I59+N(K59)),MAX(0,I59-N(K59)))
A60: S2 | B60: RIVIERA-PROJET | C60: RIVIERA | D60: Travaux | E60: BCC 0014 | F60: 8-CFO - Courants forts | H60: -333541.25 | I60: =H60*'Reporting Hebdo'!$E$3 | J60: O | M60: =IF(I60<0,MIN(0,I60+N(K60)),MAX(0,I60-N(K60)))
A61: S2 | B61: RIVIERA-PROJET | C61: RIVIERA | D61: Travaux | E61: BCC 0015 | F61: 9-CFA - Courants faibles | H61: -54877.41 | I61: =H61*'Reporting Hebdo'!$E$3 | J61: O | M61: =IF(I61<0,MIN(0,I61+N(K61)),MAX(0,I61-N(K61)))
A62: S2 | B62: RIVIERA-PROJET | C62: RIVIERA | D62: Travaux | E62: BCC 0016 | F62: 10-Climatisation & Ventilation | H62: -141680.23 | I62: =H62*'Reporting Hebdo'!$E$3 | J62: O | M62: =IF(I62<0,MIN(0,I62+N(K62)),MAX(0,I62-N(K62)))
A63: S2 | B63: RIVIERA-PROJET | C63: RIVIERA | D63: Travaux | E63: BCC 0017 | F63: 11-Plomberie RIA - FC | H63: -207907.04 | I63: =H63*'Reporting Hebdo'!$E$3 | J63: O | M63: =IF(I63<0,MIN(0,I63+N(K63)),MAX(0,I63-N(K63)))
A64: S2 | B64: RIVIERA-PROJET | C64: RIVIERA | D64: Honoraires | E64: HON 0007 | F64: E&S | G64: INSUCO / BRL INGENIERIE/ANDE | H64: -6719.33 | I64: =H64*'Reporting Hebdo'!$E$3 | J64: O | M64: =IF(I64<0,MIN(0,I64+N(K64)),MAX(0,I64-N(K64)))
A65: S2 | B65: RIVIERA-PROJET | C65: RIVIERA | D65: Honoraires | E65: HON 0010 | F65: Retenue à la source (prestataires étrangers) | H65: -4100.35 | I65: =H65*'Reporting Hebdo'!$E$3 | J65: O | M65: =IF(I65<0,MIN(0,I65+N(K65)),MAX(0,I65-N(K65)))
A66: S2 | B66: RIVIERA-PROJET | C66: RIVIERA | D66: Autres dépenses | E66: AUD 0007 | F66: Frais Divers | G66: THINKSTEP / YABA & KUMBA / DOUG AND WOLF / CHANAN / REAL CONSULTING / HORECAF / GILLES DEVENDEVILLE | H66: -11683 | I66: =H66*'Reporting Hebdo'!$E$3 | J66: O | M66: =IF(I66<0,MIN(0,I66+N(K66)),MAX(0,I66-N(K66)))
A67: S2 | B67: RIVIERA-PROJET | C67: RIVIERA | D67: Autres dépenses | E67: AUD 0008 | F67: Publicité | G67: SHERPA/LES ATELIERS COOK IMPRIM | H67: -3000 | I67: =H67*'Reporting Hebdo'!$E$3 | J67: O | M67: =IF(I67<0,MIN(0,I67+N(K67)),MAX(0,I67-N(K67)))
A68: S2 | B68: RIVIERA-PROJET | C68: RIVIERA | D68: Autres dépenses | E68: AUD 0009 | F68: Honoraires Juridiques et Fiscaux | G68: KSK / MONDON / CHAUVEAU | H68: -35480 | I68: =H68*'Reporting Hebdo'!$E$3 | J68: O | M68: =IF(I68<0,MIN(0,I68+N(K68)),MAX(0,I68-N(K68)))
A69: S2 | B69: RIVIERA-PROJET | C69: RIVIERA | D69: Frais financiers | E69: FFI 0003 | F69: Frais intercalaires | H69: -504987.37 | I69: =H69*'Reporting Hebdo'!$E$3 | J69: O | M69: =IF(I69<0,MIN(0,I69+N(K69)),MAX(0,I69-N(K69)))
A70: S2 | B70: RIVIERA-PROJET | C70: RIVIERA | D70: Frais financiers | E70: FFI 0004 | F70: Commissions d'engagement | H70: -8404.26 | I70: =H70*'Reporting Hebdo'!$E$3 | J70: O | M70: =IF(I70<0,MIN(0,I70+N(K70)),MAX(0,I70-N(K70)))
A71: S4 | B71: TERASSON-PROJET | C71: TERASSON | D71: Honoraires | E71: HON 0002 | F71: BET / MOE / SSI | G71: SCO | H71: -20580.8 | I71: =H71*'Reporting Hebdo'!$E$3 | J71: O | M71: =IF(I71<0,MIN(0,I71+N(K71)),MAX(0,I71-N(K71)))
A72: S4 | B72: RIVIERA-PROJET | C72: RIVIERA | D72: Honoraires | E72: HON 0002 | F72: BET / MOE / SSI | G72: SCO | H72: -20699.65 | I72: =H72*'Reporting Hebdo'!$E$3 | J72: O | M72: =IF(I72<0,MIN(0,I72+N(K72)),MAX(0,I72-N(K72)))
A73: Nov. 2026 | B73: TERASSON-PROJET | C73: TERASSON | D73: Travaux | E73: BCC 0008 | F73: Travaux aménagements preneurs | H73: -11750 | I73: =H73*'Reporting Hebdo'!$E$3 | J73: O | M73: =IF(I73<0,MIN(0,I73+N(K73)),MAX(0,I73-N(K73)))
A74: Nov. 2026 | B74: TERASSON-PROJET | C74: TERASSON | D74: Travaux | E74: BCC 0009 | F74: Autres travaux | H74: -12500 | I74: =H74*'Reporting Hebdo'!$E$3 | J74: O | M74: =IF(I74<0,MIN(0,I74+N(K74)),MAX(0,I74-N(K74)))
A75: Nov. 2026 | B75: TERASSON-PROJET | C75: TERASSON | D75: Travaux | E75: BCC 0017 | F75: 02 GROS ŒUVRE & INSTALLATION DE CHANTIER | H75: -598630.99 | I75: =H75*'Reporting Hebdo'!$E$3 | J75: O | M75: =IF(I75<0,MIN(0,I75+N(K75)),MAX(0,I75-N(K75)))
A76: Nov. 2026 | B76: TERASSON-PROJET | C76: TERASSON | D76: Travaux | E76: BCC 0018 | F76: 03 ETANCHEITE | H76: -52358.11 | I76: =H76*'Reporting Hebdo'!$E$3 | J76: O | M76: =IF(I76<0,MIN(0,I76+N(K76)),MAX(0,I76-N(K76)))
A77: Nov. 2026 | B77: TERASSON-PROJET | C77: TERASSON | D77: Travaux | E77: BCC 0026 | F77: 10 CLIMATISATION / VENTILATION / DESENFUMAGE | H77: -20266.96 | I77: =H77*'Reporting Hebdo'!$E$3 | J77: O | M77: =IF(I77<0,MIN(0,I77+N(K77)),MAX(0,I77-N(K77)))
A78: Nov. 2026 | B78: TERASSON-PROJET | C78: TERASSON | D78: Travaux | E78: BCC 0027 | F78: 11 PLOMBERIE / RIA | H78: -5391.59 | I78: =H78*'Reporting Hebdo'!$E$3 | J78: O | M78: =IF(I78<0,MIN(0,I78+N(K78)),MAX(0,I78-N(K78)))
A79: Nov. 2026 | B79: TERASSON-PROJET | C79: TERASSON | D79: Travaux | E79: BCC 0028 | F79: 12 REVETEMENTS DURS & SOUPLES | H79: -2149.39 | I79: =H79*'Reporting Hebdo'!$E$3 | J79: O | M79: =IF(I79<0,MIN(0,I79+N(K79)),MAX(0,I79-N(K79)))
A80: Nov. 2026 | B80: TERASSON-PROJET | C80: TERASSON | D80: Travaux | E80: BCC 0029 | F80: 13 FP & CLOISONNEMENT | H80: -21726.3 | I80: =H80*'Reporting Hebdo'!$E$3 | J80: O | M80: =IF(I80<0,MIN(0,I80+N(K80)),MAX(0,I80-N(K80)))
A81: Nov. 2026 | B81: TERASSON-PROJET | C81: TERASSON | D81: Travaux | E81: BCC 0030 | F81: 14 PEINTURE | H81: -13508.13 | I81: =H81*'Reporting Hebdo'!$E$3 | J81: O | M81: =IF(I81<0,MIN(0,I81+N(K81)),MAX(0,I81-N(K81)))
A82: Nov. 2026 | B82: TERASSON-PROJET | C82: TERASSON | D82: Travaux | E82: BCC 0034 | F82: CC ROOFTOP SURELEVATION BAT B | H82: -58400 | I82: =H82*'Reporting Hebdo'!$E$3 | J82: O | M82: =IF(I82<0,MIN(0,I82+N(K82)),MAX(0,I82-N(K82)))
A83: Nov. 2026 | B83: TERASSON-PROJET | C83: TERASSON | D83: Honoraires | E83: HON 0001 | F83: Architecte | G83: ARCHICONCEPT / MAP | H83: -6577 | I83: =H83*'Reporting Hebdo'!$E$3 | J83: O | M83: =IF(I83<0,MIN(0,I83+N(K83)),MAX(0,I83-N(K83)))
A84: Nov. 2026 | B84: TERASSON-PROJET | C84: TERASSON | D84: Honoraires | E84: HON 0002 | F84: BET / MOE / SSI | G84: SCO | H84: -20580.8 | I84: =H84*'Reporting Hebdo'!$E$3 | J84: O | M84: =IF(I84<0,MIN(0,I84+N(K84)),MAX(0,I84-N(K84)))
A85: Nov. 2026 | B85: TERASSON-PROJET | C85: TERASSON | D85: Honoraires | E85: HON 0006 | F85: CSPS | G85: SOCOTEC | H85: -4878.37 | I85: =H85*'Reporting Hebdo'!$E$3 | J85: O | M85: =IF(I85<0,MIN(0,I85+N(K85)),MAX(0,I85-N(K85)))
A86: Nov. 2026 | B86: TERASSON-PROJET | C86: TERASSON | D86: Honoraires | E86: HON 0007 | F86: E&S | G86: ANDE / ENVAL / INSUCO / BIOTOPE / IVOIRE HYDROGENE | H86: -4827.48 | I86: =H86*'Reporting Hebdo'!$E$3 | J86: O | M86: =IF(I86<0,MIN(0,I86+N(K86)),MAX(0,I86-N(K86)))
A87: Nov. 2026 | B87: TERASSON-PROJET | C87: TERASSON | D87: Honoraires | E87: HON 0010 | F87: Retenue à la source (prestataires étrangers) | H87: -566.74 | I87: =H87*'Reporting Hebdo'!$E$3 | J87: O | M87: =IF(I87<0,MIN(0,I87+N(K87)),MAX(0,I87-N(K87)))
A88: Nov. 2026 | B88: TERASSON-PROJET | C88: TERASSON | D88: Autres dépenses | E88: AUD 0008 | F88: Publicité | G88: SHERPA | H88: -5000 | I88: =H88*'Reporting Hebdo'!$E$3 | J88: O | M88: =IF(I88<0,MIN(0,I88+N(K88)),MAX(0,I88-N(K88)))
A89: Nov. 2026 | B89: TERASSON-PROJET | C89: TERASSON | D89: Autres dépenses | E89: AUD 0009 | F89: Honoraires Juridiques et Fiscaux | G89: MAZARS/DWF | H89: -42996.69 | I89: =H89*'Reporting Hebdo'!$E$3 | J89: O | M89: =IF(I89<0,MIN(0,I89+N(K89)),MAX(0,I89-N(K89)))
A90: Nov. 2026 | B90: TERASSON-PROJET | C90: TERASSON | D90: Honoraires de vente | E90: HOV 0004 | F90: Fonds de concours | H90: -313500 | I90: =H90*'Reporting Hebdo'!$E$3 | J90: O | M90: =IF(I90<0,MIN(0,I90+N(K90)),MAX(0,I90-N(K90)))
A91: Nov. 2026 | B91: TERASSON-PROJET | C91: TERASSON | D91: Honoraires de vente | E91: HOV 0005 | F91: FF&E RT | H91: -358671 | I91: =H91*'Reporting Hebdo'!$E$3 | J91: O | M91: =IF(I91<0,MIN(0,I91+N(K91)),MAX(0,I91-N(K91)))
A92: Nov. 2026 | B92: TERASSON-PROJET | C92: TERASSON | D92: Frais financiers | E92: FFI 0003 | F92: Frais intercalaires | G92: IFC/PROPARCO | H92: -289547.42 | I92: =H92*'Reporting Hebdo'!$E$3 | J92: O | M92: =IF(I92<0,MIN(0,I92+N(K92)),MAX(0,I92-N(K92)))
A93: Nov. 2026 | B93: TERASSON-PROJET | C93: TERASSON | D93: Frais financiers | E93: FFI 0004 | F93: Commissions d'engagement | G93: IFC/PROPARCO | H93: -44236.41 | I93: =H93*'Reporting Hebdo'!$E$3 | J93: O | M93: =IF(I93<0,MIN(0,I93+N(K93)),MAX(0,I93-N(K93)))
A94: Nov. 2026 | B94: RIVIERA-PROJET | C94: RIVIERA | D94: Travaux | E94: BCC 0010 | F94: Exonérations Douanières | H94: 200000 | I94: =H94*'Reporting Hebdo'!$E$3 | J94: O | M94: =IF(I94<0,MIN(0,I94+N(K94)),MAX(0,I94-N(K94)))
A95: Nov. 2026 | B95: RIVIERA-PROJET | C95: RIVIERA | D95: Travaux | E95: BCC 0013 | F95: 1B-VRD - Espaces verts | G95: UNISERV | H95: -87897.35 | I95: =H95*'Reporting Hebdo'!$E$3 | J95: O | M95: =IF(I95<0,MIN(0,I95+N(K95)),MAX(0,I95-N(K95)))
A96: Nov. 2026 | B96: RIVIERA-PROJET | C96: RIVIERA | D96: Travaux | E96: BCC 0014 | F96: 2-Gros oeuvre | H96: -645447.27 | I96: =H96*'Reporting Hebdo'!$E$3 | J96: O | M96: =IF(I96<0,MIN(0,I96+N(K96)),MAX(0,I96-N(K96)))
A97: Nov. 2026 | B97: RIVIERA-PROJET | C97: RIVIERA | D97: Travaux | E97: BCC 0016 | F97: 4A-Charpente metallique | H97: -76680.35 | I97: =H97*'Reporting Hebdo'!$E$3 | J97: O | M97: =IF(I97<0,MIN(0,I97+N(K97)),MAX(0,I97-N(K97)))
A98: Nov. 2026 | B98: RIVIERA-PROJET | C98: RIVIERA | D98: Honoraires | E98: HON 0001 | F98: Architecte | G98: ZUO / CIA / MAP | H98: -18066.62 | I98: =H98*'Reporting Hebdo'!$E$3 | J98: O | M98: =IF(I98<0,MIN(0,I98+N(K98)),MAX(0,I98-N(K98)))
A99: Nov. 2026 | B99: RIVIERA-PROJET | C99: RIVIERA | D99: Honoraires | E99: HON 0002 | F99: BET / MOE / SSI | G99: SCO | H99: -20699.65 | I99: =H99*'Reporting Hebdo'!$E$3 | J99: O | M99: =IF(I99<0,MIN(0,I99+N(K99)),MAX(0,I99-N(K99)))
A100: Nov. 2026 | B100: RIVIERA-PROJET | C100: RIVIERA | D100: Honoraires | E100: HON 0007 | F100: E&S | G100: INSUCO / BRL INGENIERIE/ANDE | H100: -6719.33 | I100: =H100*'Reporting Hebdo'!$E$3 | J100: O | M100: =IF(I100<0,MIN(0,I100+N(K100)),MAX(0,I100-N(K100)))
A101: Nov. 2026 | B101: RIVIERA-PROJET | C101: RIVIERA | D101: Honoraires | E101: HON 0009 | F101: Divers honoraires | G101: AUXO / PROJEX / GSPM / HORECAF / HILLEL | H101: -10000 | I101: =H101*'Reporting Hebdo'!$E$3 | J101: O | M101: =IF(I101<0,MIN(0,I101+N(K101)),MAX(0,I101-N(K101)))
...

Sheet Position CI 30-09
A1: Position de trésorerie CI – soldes bancaires au 30/09/2026
A2: Solde FCFA (colonne F, en jaune) modifiable : le reporting et l'équilibrage se recalculent. Colonne J : solde d'origine de la position CI.
A4: Entité | B4: Banque | C4: Compte | D4: Destination (position CI) | E4: Bloc du reporting | F4: Solde FCFA | G4: Solde € | H4: Clé | I4: Source | J4: Solde position CI (origine) | K4: Écart (mise à jour)
A5: PICI | B5: SOCIETE GENERALE | C5: SOCIETE GENERALE-PICI | D5: Dédié besoin de fonctionnement et "Netting" autres compagnies CIV | E5: Compte de société | F5: 3580753 | G5: =F5/'Reporting Hebdo'!$E$3 | H5: PICI | I5: CIV position, ligne 5 | J5: 3580753 | K5: =F5-J5
A6: PICI | B6: STANBIC | C6: STANBIC-PICI | D6: Dédié besoin de fonctionnement | E6: Compte de société | F6: 24751125 | G6: =F6/'Reporting Hebdo'!$E$3 | H6: PICI | I6: CIV position, ligne 6 | J6: 24751125 | K6: =F6-J6
A7: PICI | B7: ECOBANK | C7: ECOBANK-PICI | D7: Dédié besoin de fonctionnement | E7: Compte de société | F7: -336430487 | G7: =F7/'Reporting Hebdo'!$E$3 | H7: PICI | I7: CIV position, ligne 7 | J7: 368235073 | K7: =F7-J7
A8: FIRST | B8: SOCIETE GENERALE | C8: SOCIETE GENERALE-FIRST | D8: Dédié besoin de fonctionnement | E8: Compte de société | F8: 8429337 | G8: =F8/'Reporting Hebdo'!$E$3 | H8: FIRST | I8: CIV position, ligne 9 | J8: 8429337 | K8: =F8-J8
A9: FIRST | B9: STANBIC | C9: STANBIC-FIRST | D9: Dédié besoin de fonctionnement | E9: Compte de société | F9: 227694317 | G9: =F9/'Reporting Hebdo'!$E$3 | H9: FIRST | I9: CIV position, ligne 10 | J9: 227694317 | K9: =F9-J9
A10: TERASSON | B10: SOCIETE GENERALE | C10: SOCIETE GENERALE-TERASSON | D10: Dédié besoin de fonctionnement | E10: Compte de société | F10: 58193022 | G10: =F10/'Reporting Hebdo'!$E$3 | H10: TERASSON | I10: CIV position, ligne 15 | J10: 58193022 | K10: =F10-J10
A11: TERASSON | B11: ECOBANK | C11: ECOBANK -TERASSON | D11: Dédié besoin de fonctionnement | E11: Compte de société | F11: 62000 | G11: =F11/'Reporting Hebdo'!$E$3 | H11: TERASSON | I11: CIV position, ligne 16 | J11: 62000 | K11: =F11-J11
A12: RIVIERA | B12: SOCIETE GENERALE | C12: SOCIETE GENERALE-RIVIERA | D12: Dédié besoin de fonctionnement | E12: Compte de société | F12: 1473216 | G12: =F12/'Reporting Hebdo'!$E$3 | H12: RIVIERA | I12: CIV position, ligne 19 | J12: 1473216 | K12: =F12-J12
A13: RIVIERA | B13: BNI | C13: BNI-RIVIERA(Courant) | D13: Affection placement? Ou besoin de fonctionnement | E13: Compte dédié | F13: 1771977229 | G13: =F13/'Reporting Hebdo'!$E$3 | H13: RIVIERA-ARBITRER | I13: CIV position, ligne 20 | J13: 1771977229 | K13: =F13-J13
A14: SCO AO | B14: BANK OF AFRICA | C14: BANK OF AFRICA-SCO AO | D14: Dédié besoin de fonctionnement | E14: Compte de société | F14: 897338 | G14: =F14/'Reporting Hebdo'!$E$3 | H14: SCO AO | I14: CIV position, ligne 23 | J14: 897338 | K14: =F14-J14
A15: SCO AO | B15: BANQUE ATLANTIQUE | C15: BACI-CompteCourant | D15: Dédié besoin de fonctionnement | E15: Compte de société | F15: 5375161 | G15: =F15/'Reporting Hebdo'!$E$3 | H15: SCO AO | I15: CIV position, ligne 24 | J15: 5375161 | K15: =F15-J15
A16: SCO AO | B16: BANQUE ATLANTIQUE | C16: BACI-Projet | D16: Dédié paiement Projet SCO | E16: Compte de société | F16: 22569647 | G16: =F16/'Reporting Hebdo'!$E$3 | H16: SCO AO | I16: CIV position, ligne 25 | J16: 22569647 | K16: =F16-J16
... A24: IMMONEUF | B24: ECOBANK | C24: ECOBANK-IMMONEUF | D24: Dédié besoin de fonctionnement | E24: Compte de société | F24: 36000 | G24: =F24/'Reporting Hebdo'!$E$3 | H24: IMMONEUF | I24: CIV position, ligne 36 | J24: 36000 | K24: =F24-J24
A25: IMMONEUF | C25: BACI - IMMONEUF | D25: Dédié besoin de fonctionnement | E25: Compte de société | F25: 58000 | G25: =F25/'Reporting Hebdo'!$E$3 | H25: IMMONEUF | I25: CIV position, ligne 37 | J25: 58000 | K25: =F25-J25
A26: INFI SOFT | B26: SIB | C26: INFI SOFT - SIB | D26: Dédié besoin de fonctionnement | E26: Compte de société | F26: 2751880 | G26: =F26/'Reporting Hebdo'!$E$3 | H26: INFI SOFT | I26: CIV position, ligne 39 | J26: 2751880 | K26: =F26-J26
A27: ODALYS CI | B27: SOCIETE GENERALE | C27: SOCIETE GENERALE-ODALYS | D27: Dédié besoin de fonctionnement | E27: Compte de société | F27: 6062002 | G27: =F27/'Reporting Hebdo'!$E$3 | H27: ODALYS CI | I27: CIV position, ligne 41 | J27: 6062002 | K27: =F27-J27
A28: RIVIERA | B28: BNI | C28: BNI-PICI / Fonds projet RP | D28: Dédié paiement CPI | E28: Compte dédié | F28: 2643139493 | G28: =F28/'Reporting Hebdo'!$E$3 | H28: RIVIERA-PROJET | I28: CIV position, ligne 46 | J28: 2643139493 | K28: =F28-J28
A29: TERASSON | B29: BNI | C29: BNI-TERASSON / Fonds projet NP | D29: Dédié paiement CPI | E29: Compte dédié | F29: 1481904490 | G29: =F29/'Reporting Hebdo'!$E$3 | H29: TERASSON-PROJET | I29: CIV position, ligne 47 | J29: 1481904490 | K29: =F29-J29
A30: SCO AO | C30: BACI-AGORA/COMPTE BLOQU. TVA | D30: DSR/Augmentation/LL/Disbursment | E30: Compte dédié | F30: 76268390 | G30: =F30/'Reporting Hebdo'!$E$3 | H30: SCO AO-BACIAGORACOMPTEBLOQUTVA | I30: CIV position, ligne 49 | J30: 76268390 | K30: =F30-J30
A31: TOTAL | F31: =SUM(F5:F30) | G31: =SUM(G5:G30)
A34: Comptes indisponibles – exclus de la position (pour information)
A35: FIRST | B35: STANBIC | C35: STANBIC-FIRST _ Debt Service | D35: DSR/Augmentation/LL/Disbursment | E35: Indisponible | F35: 350727089 | G35: =F35/'Reporting Hebdo'!$E$3 | I35: CIV position, ligne 11 | J35: 350727089
A36: FIRST | B36: STANBIC | C36: STANBIC-FIRST_LL | D36: DSR/Augmentation/LL/Disbursment | E36: Indisponible | F36: 42500000 | G36: =F36/'Reporting Hebdo'!$E$3 | I36: CIV position, ligne 12 | J36: 42500000
A37: FIRST | B37: STANBIC | C37: STANBIC-FIRST_Disbursement | D37: DSR/Augmentation/LL/Disbursment | E37: Indisponible | F37: 26289357 | G37: =F37/'Reporting Hebdo'!$E$3 | I37: CIV position, ligne 13 | J37: 26289357
A38: RIVIERA | B38: BNI | C38: BNI-RIVIERA(Augmentation) | D38: DSR/Augmentation/LL/Disbursment | E38: Indisponible | F38: 0 | G38: =F38/'Reporting Hebdo'!$E$3 | I38: CIV position, ligne 21 | J38: 0
A39: RIVIERA | B39: BNI | C39: BNI-RIVIERA(DSRA) / Placement | D39: DSR/Augmentation/LL/Disbursment | E39: Indisponible | F39: 776110097 | G39: =F39/'Reporting Hebdo'!$E$3 | I39: CIV position, ligne 48 | J39: 776110097
A40: Total indisponible | F40: =SUM(F35:F39)

Sheet Contrôles
A1: Contrôles de cohérence entre les sources et le reporting
A3: 1. Soldes bancaires au 30/09/2026 (FCFA)
A4: Contrôle | B4: Reporting | C4: Position CI | D4: Écart | E4: Commentaire
A5: Total comptes de sociétés + comptes dédiés | B5: ='Reporting Hebdo'!M52 | C5: ='Position CI 30-09'!F31 | D5: =B5-C5 | E5: Somme des lignes bancaires disponibles de la feuille « CIV position » (comptes indisponibles exclus).
A7: 2. Fonctionnement : reporting vs RECAP de l'audit (S1 à S4 de l'audit, M FCFA)
A8: Entité | B8: Reporting (fournisseurs, impôts, cotisations, salaires, prêts) | C8: RECAP de l'audit | D8: Écart | E8: Commentaire
A9: PICI | B9: 296.57724 | C9: 296.57724 | D9: =B9-C9 | E9: Toutes les semaines de l'audit sont dans l'horizon S1 à S5
A10: FIRST | B10: 540.96836 | C10: 540.96836 | D10: =B10-C10 | E10: Toutes les semaines de l'audit sont dans l'horizon S1 à S5
A11: TERASSON | B11: 264.6339 | C11: 264.6339 | D11: =B11-C11 | E11: Toutes les semaines de l'audit sont dans l'horizon S1 à S5
A12: RIVIERA | B12: 88.788492 | C12: 88.788492 | D12: =B12-C12 | E12: Toutes les semaines de l'audit sont dans l'horizon S1 à S5
A13: RHD CI | B13: 50.022534 | C13: 50.022534 | D13: =B13-C13 | E13: Toutes les semaines de l'audit sont dans l'horizon S1 à S5
A14: IMMONEUF | B14: 77.778338 | C14: 77.778338 | D14: =B14-C14 | E14: Toutes les semaines de l'audit sont dans l'horizon S1 à S5
A15: FINAFRICA | B15: 233.76346 | C15: 233.76346 | D15: =B15-C15 | E15: Toutes les semaines de l'audit sont dans l'horizon S1 à S5
A16: ODALYS CI | B16: 9.5751 | C16: 9.5751 | D16: =B16-C16 | E16: Toutes les semaines de l'audit sont dans l'horizon S1 à S5
A17: AB CENTER | B17: 6.289 | C17: 6.289 | D17: =B17-C17 | E17: Toutes les semaines de l'audit sont dans l'horizon S1 à S5
A19: 3. Projets : montants non réglés des cash plans (€ HT)
A20: Projet / période | B20: Reporting | C20: Bilan financier | D20: Écart | E20: Source
A21: RIVIERA – S1 à S5 (antériorités + mois suivant) | B21: =-SUMIFS('Détail projets & dettes'!$H$5:$H$500,'Détail projets & dettes'!$C$5:$C$500,"RIVIERA",'Détail projets & dettes'!$J$5:$J$500,"O",'Détail projets & dettes'!$A$5:$A$500,"S*") | C21: 4946194.2 | D21: =B21-C21 | E21: 996d2c11-2026-10-02_RIVIERA_Bilan_financier.xlsm
A22: TERASSON – S1 à S5 (antériorités + mois suivant) | B22: =-SUMIFS('Détail projets & dettes'!$H$5:$H$500,'Détail projets & dettes'!$C$5:$C$500,"TERASSON",'Détail projets & dettes'!$J$5:$J$500,"O",'Détail projets & dettes'!$A$5:$A$500,"S*") | C22: 4097563.7 | D22: =B22-C22 | E22: bee511f1-2026-10-02_Village_notre_p_re_Bilan_financier.xlsm
A24: 4. Lignes non retenues (Retenu = N) – à revoir
A25: Motif / libellé | B25: Montant FCFA | C25: Nombre de lignes | E25: Feuille
A26: FOURNISSEURS - FGX – intragroupe | B26: -13254203304 | C26: 17 | E26: Détail fonctionnement
A27: ENREGISTREMENTS – droits d'enregistrement | B27: -1715342550 | C27: 5 | E27: Détail fonctionnement
A28: ENCAISSEMENTS – autre | B28: 6113285 | C28: 1 | E28: Détail fonctionnement
A29: Remboursement de prêt – prêts des projets (déjà dans les cash plans) | B29: -220402934 | C29: 2 | E29: Détail projets & dettes
A31: Alertes de lecture
A32: SCO AO : 15 ligne(s) du reporting modifié remplacées par la prévision de trésorerie SCO.
A33: Paiements exécutés : 4 paiement(s), 704,7 M ; 704,7 M imputés sur le besoin S1 à S5, déduits du solde des comptes débités.

Sheet Comparaison RCI
A1: Comparaison avec la présentation RCI (Laureen) – mêmes sources, M FCFA
A3: 1. Fonctionnement par entité
A4: Entité | B4: Besoin RCI | C4: Besoin reporting | D4: Écart | E4: Trésorerie RCI | F4: Trésorerie reporting | G4: Position RCI | H4: Position reporting | I4: Écart de position | J4: Explication
A5: PICI | B5: 296.57724 | C5: 296.57724 | D5: 0 | E5: 396.56695 | F5: -308.09861 | G5: 99.989712 | H5: -604.67585 | I5: -704.66556 | J5: Même besoin · Trésorerie : -704,7 (comptes « Dédié paiement Projet SCO » ou comptes non classés en fonctionnement)
A6: FIRST | B6: 540.96836 | C6: 540.96836 | D6: 0 | E6: 236.12365 | F6: 236.12365 | G6: -175.27644 | H6: -175.27644 | I6: -5.6843419e-14 | J6: Même besoin
A7: TERASSON | B7: 264.6339 | C7: 264.6339 | D7: 0 | E7: 58.255022 | F7: 58.255022 | G7: -206.37888 | H7: -206.37888 | I7: 0 | J7: Même besoin
A8: RIVIERA | B8: 88.788492 | C8: 88.788492 | D8: 0 | E8: 1.473216 | F8: 1.473216 | G8: -87.315276 | H8: -87.315276 | I8: 1.4210855e-14 | J8: Même besoin
A9: SCO AO | C9: 178.04563 | D9: 178.04563 | F9: 29.131434 | H9: -29.54598 | I9: -29.54598 | J9: Hors périmètre de la présentation RCI (aucune ligne dans le RECAP) ; flux repris du reporting de Christophe
A10: FINAFRICA | B10: 233.76346 | C10: 233.76346 | D10: -2.8421709e-14 | E10: 35.073732 | F10: 35.073732 | G10: -198.68973 | H10: -198.68973 | I10: 2.8421709e-14 | J10: Même besoin
A11: AB CENTER | B11: 6.289 | C11: 6.289 | D11: 0 | E11: -0.012342 | F11: -0.012342 | G11: -6.301342 | H11: -6.301342 | I11: 0 | J11: Même besoin
A12: IMMONEUF | B12: 77.778338 | C12: 77.778338 | D12: 0 | E12: 11.764561 | F12: 11.764561 | G12: -66.013777 | H12: -66.013777 | I12: -1.4210855e-14 | J12: Même besoin
A13: INFI SOFT | C13: 0 | D13: 0 | F13: 2.75188 | H13: 2.75188 | I13: 2.75188 | J13: Hors périmètre de la présentation RCI (aucune ligne dans le RECAP)
A14: ODALYS CI | B14: 9.5751 | C14: 9.5751 | D14: 0 | E14: 6.062002 | F14: 6.062002 | G14: -3.513098 | H14: -3.513098 | I14: -1.7763568e-15 | J14: Même besoin
A15: RHD CI | B15: 50.022534 | C15: 50.022534 | D15: 0 | E15: 0 | F15: 0 | G15: -50.022534 | H15: -50.022534 | I15: -1.4210855e-14 | J15: Même besoin
A16: Total | B16: 1568.3964 | C16: 1746.4421 | D16: 178.04563 | E16: 745.3068 | F16: 72.52455 | G16: -693.52136 | H16: -1424.981 | I16: -731.45966
A18: 2. Fonctionnement par poste
A19: Poste | B19: RCI | C19: Reporting | D19: Écart | E19: Explication
A20: Fournisseurs | B20: 244.99626 | C20: 244.99626 | D20: 0 | E20: Identique (mêmes lignes du RECAP / de la balance)
A21: Impôts | B21: 637.4058 | C21: 637.4058 | D21: 0 | E21: Identique (mêmes lignes du RECAP / de la balance)
A22: Cotisations sociales | B22: 152.07069 | C22: 152.07069 | D22: 0 | E22: Identique (mêmes lignes du RECAP / de la balance)
A23: Salaires | B23: 85.788691 | C23: 85.788691 | D23: 0 | E23: Identique (mêmes lignes du RECAP / de la balance)
A24: Remboursement de prêts | B24: 448.13498 | C24: 448.13498 | D24: 0 | E24: Identique (mêmes lignes du RECAP / de la balance)
A25: Loyers à encaisser | B25: 129.56827 | C25: 129.56827 | D25: -2.8421709e-14 | E25: Identique (mêmes lignes du RECAP / de la balance)
A26: Entités hors présentation RCI | B26: 0 | C26: 178.04563 | D26: 178.04563 | E26: SCO AO 178,0
A28: 3. Projets par mois (cash plans, € HT convertis)
A29: Projet / mois | B29: RCI (montant du mois) | C29: Reporting (non réglé) | D29: Écart | E29: Explication
A30: RIVIERA | B30: 3699.5668 | C30: 3699.5668 | D30: 4.5474735e-13 | E30: Total : fenêtre RCI septembre à novembre 2026 ; reporting = antériorités non réglées + mois suivant (S1 à S5) + mois d'après (information)
A31: dont antériorités (déc. 2025) | B31: 91.26995 | C31: 91.26995 | D31: 0 | E31: Montants non réglés des mois antérieurs, reportés en S1 / sur le premier mois des deux côtés
A32: septembre 2026 + antériorités | B32: 1976.5851 | C32: 1976.5851 | D32: 0 | E32: Identique
A33: octobre 2026 | B33: 1267.9056 | C33: 1267.9056 | D33: 2.2737368e-13 | E33: Identique
A34: novembre 2026 | B34: 455.07613 | C34: 455.07613 | D34: -1.1368684e-13 | E34: Identique
A35: Trésorerie dédiée (CPI) | B35: 2643.1395 | C35: 2643.1395 | D35: 0 | E35: Identique
A36: TERASSON | B36: 3926.314 | C36: 3221.6484 | D36: -704.66556 | E36: Total : fenêtre RCI septembre à novembre 2026 ; reporting = antériorités non réglées + mois suivant (S1 à S5) + mois d'après (information)
A37: dont antériorités (déc. 2025, août 2026) | B37: 116.22847 | C37: 116.22847 | D37: 1.4210855e-14 | E37: Montants non réglés des mois antérieurs, reportés en S1 / sur le premier mois des deux côtés
A38: septembre 2026 + antériorités | B38: 2197.7624 | C38: 2197.7624 | D38: 0 | E38: Identique
A39: octobre 2026 | B39: 490.06317 | C39: 490.06317 | D39: 0 | E39: Identique
A40: novembre 2026 | B40: 1238.4884 | C40: 1238.4884 | D40: -2.2737368e-13 | E40: Identique
A41: Trésorerie dédiée (CPI) | B41: 1481.9045 | C41: 1481.9045 | D41: 0 | E41: Identique
A43: 4. Différences de conventions
A44: • Semaines : la présentation RCI suit les semaines de l'audit (28/09 → 25/10/2026) ; le reporting démarre en S1 au 05/10 et y reporte toutes les antériorités. Les montants de l'audit sont les mêmes, seule leur semaine change.
A45: • Projets : la présentation RCI prend les cash plans de septembre à novembre 2026 (tous montants du mois, antériorités non réglées reportées sur le premier mois) ; le reporting prend les montants non réglés (antériorités en S1, mois suivant par semaine, mois d'après pour information).
A46: • Trésorerie : compte(s) à destination non tranchée non comptés dans le reporting, non comptés dans la présentation RCI.
A47: • Périmètre : SCO AO ne figure(nt) que dans le reporting.
A48: • Droits d'enregistrement : exclus des deux côtés.
A49: • Loyers : octobre 2026, encaissement placé en S2 en fonctionnement de FIRST.
A50: • Comptes indisponibles exclus de la position du reporting : STANBIC-FIRST _ Debt Service, STANBIC-FIRST_LL, STANBIC-FIRST_Disbursement, BNI-RIVIERA(Augmentation), BNI-RIVIERA(DSRA) / Placement (1 195,6 M). La présentation RCI exclut aussi ces fonds (DSR, augmentation, LL, disbursement).

Sheet Paiements exécutés
A1: Paiements exécutés depuis la position – diminution des besoins
A2: Montant imputé : déduit du reste à payer des lignes indiquées (feuilles de détail, colonnes « Payé »). Déduit du solde = O : montant retiré du solde du compte débité dans la position.
A4: Réf. | B4: Date | C4: Compte débité | D4: Bénéficiaire | E4: Projet | F4: Entité | G4: Montant payé FCFA | H4: Imputé sur | I4: Répartition | J4: Imputé S1 à S5 FCFA | K4: Non imputé / hors horizon FCFA | L4: Déduit du solde
A5: PX|ECOBANK-PICI|TGCC|07/10/2026|19324742|0 | B5: 07/10/2026 | C5: ECOBANK-PICI | D5: TGCC | E5: NOTRE PÈRE | F5: TERASSON | G5: 19324742 | H5: BCC 0017 02 GROS ŒUVRE & INSTALLATION DE CHANTIER | I5: S1 19,3 M | J5: 19324742 | K5: 0 | L5: O
A6: PX|ECOBANK-PICI|TGCC|07/10/2026|629862023|1 | B6: 07/10/2026 | C6: ECOBANK-PICI | D6: TGCC | E6: NOTRE PÈRE | F6: TERASSON | G6: 629862023 | H6: BCC 0017 02 GROS ŒUVRE & INSTALLATION DE CHANTIER | I6: S1 373,4 M ; S2 256,5 M | J6: 629862023 | K6: 0 | L6: O
A7: PX|ECOBANK-PICI|TGCC|07/10/2026|52769692|2 | B7: 07/10/2026 | C7: ECOBANK-PICI | D7: TGCC | E7: NOTRE PÈRE | F7: TERASSON | G7: 52769692 | H7: BCC 0017 02 GROS ŒUVRE & INSTALLATION DE CHANTIER | I7: S2 52,8 M | J7: 52769692 | K7: 0 | L7: O
A8: PX|ECOBANK-PICI|HORECAF|07/10/2026|2709103|3 | B8: 07/10/2026 | C8: ECOBANK-PICI | D8: HORECAF | E8: NOTRE PÈRE | F8: TERASSON | G8: 2709103 | H8: HON 0002 BET / MOE / SSI – SCO | I8: S1 2,7 M | J8: 2709103 | K8: 0 | L8: O
F9: Total | G9: =SUM(G5:G8) | J9: =SUM(J5:J8) | K9: =SUM(K5:K8)

Sheet Méthode & sources
A1: Méthode, règles de semaine et sources
A3: Sources
A4: Soldes bancaires | B4: 52897ed3-Position_CI_-_01_10_2026.xlsx – feuille « CIV position ».
A5: Fonctionnement | B5: 7e1326ae-Audit_D_caissement_fournissseurs_RCI-300926_v10.xlsx – RECAP Semaine hors intragroupe (impôts, cotisations, salaires, prêts) et Répartition des charges (fournisseurs, détaillés et recalés sur le RECAP).
A6: Projets | B6: 996d2c11-2026-10-02_RIVIERA_Bilan_financier.xlsm ; bee511f1-2026-10-02_Village_notre_p_re_Bilan_financier.xlsm – « Marchés et Depenses HT », € HT ; statut lu sur la couleur de police (vert « Montant à étaler » et rouge « FNP » = non réglé, bleu « Total facturé » = réglé). Semaine des paiements du mois suivant : PICI Projets de l'audit.
A7: Loyers | B7: 48a6412d-Etat_pr_visionnel_des_encaissements_au_30092026_Tr_sorerie.xlsx
A8: SCO AO | B8: 4d5ac132-SCO_Mouvment_TRESO_PREVISION_OCT_051026.xlsx – prévision de trésorerie SCO (prioritaire) : encaissements clients, frais généraux (CNPS / CMU en charges sociales, DGI en impôts, personnel en salaires, autres en fournisseurs) et projets, par semaine.
A9: Mises à jour | B9: f169ee50-Reporting_Hebdo_CIV_05_10_2026_002.xlsx – reporting modifié : semaines, Retenu, montants et virements de l'équilibrage S1 repris.
A11: Règles de semaine
A12: S1 | B12: Semaine du 05/10 au 11/10 : toutes les antériorités (semaines de l'audit antérieures, factures et cash plans non réglés jusqu'au mois de la situation).
A13: Mois suivant (projets) | B13: Semaine identifiée dans PICI Projets, sinon S2.
A14: Loyers | B14: Encaissement en S2 (date non précisée dans l'état des loyers).
A15: Droits d'enregistrement | B15: Hors besoin, comme la présentation RCI (lignes conservées avec Retenu = N).
A16: Mises à jour | B16: Soldes : colonne F de la position (modifiable). Paiements effectués : montant payé et date dans les feuilles de détail (colonnes en jaune) ; seul le reste à payer alimente le reporting. Paiements non prévus : nouvelles lignes dans les feuilles de détail. Le fichier modifié se réimporte dans le générateur HTML pour refaire la présentation.
A17: Paiements exécutés | B17: 2d40a539-PAIEMENTS_EXECUTES.xlsx – chaque paiement est imputé sur les lignes de besoin du bénéficiaire (nom, sinon nature de l'audit PICI Projets), des plus anciennes aux plus récentes ; montant retiré du solde du compte débité s'il est postérieur à la position. Détail dans la feuille « Paiements exécutés ».
A18: Comptes indisponibles | B18: STANBIC-FIRST _ Debt Service, STANBIC-FIRST_LL, STANBIC-FIRST_Disbursement, BNI-RIVIERA(Augmentation), BNI-RIVIERA(DSRA) / Placement : exclus de la position et du reporting (listés pour information dans la feuille de position).
A19: Dette FIRST | B19: Échéances des prêts FIRST et loyers à encaisser traités en fonctionnement de FIRST (pas de compte dédié).
A20: Prêts des projets | B20: TERASSON et RIVIERA : frais financiers déjà dans les cash plans, non ajoutés.
A22: Conventions
A23: Signes | B23: Décaissements en négatif, encaissements en positif. Solde théorique = solde précédent + prévisions de la semaine.
A24: Devise | B24: Taux fixe 655,957 FCFA / € (cellule E3 de « Reporting Hebdo »).
A25: Retenu | B25: O = intégré au reporting ; N = conservé pour traçabilité. Passer une ligne à O l'intègre automatiquement.
A27: Équilibrage S1
A28: Compte payeur | B28: Sociétés : compte « Dédié besoin de fonctionnement » au plus gros solde ; fournisseurs projets : compte « Dédié paiement CPI » (SCO AO : BACI-Projet) ; échéances de prêts FIRST : en fonctionnement, sur le compte payeur de FIRST ; RHD CI (sans compte) : paiement par PICI pour son compte.
A29: Autres nivellements | B29: Regroupement des comptes d'une même entité sur son compte payeur ; BNI-RIVIERA courant mobilisé pour RIVIERA, sous réserve d'arbitrage.
A30: Nivellement via PICI | B30: Excédents PICI puis FIRST vers les sociétés en déficit : impôts, cotisations et salaires d'abord, fournisseurs ensuite, en commençant par les plus petits déficits.
A31: Liens | B31: Paiements : SUMIFS sur les feuilles de détail (semaine S1, Retenu = O) ; soldes : position CI ; nivellements : tableau des virements, modifiable.
